[{"owner":{"reputation":355,"user_id":4621980,"user_type":"registered","profile_image":"https://lh6.googleusercontent.com/-h6DNpY61Ggw/AAAAAAAAAAI/AAAAAAAAHSE/zAYEMrIU20o/photo.jpg?sz=128","display_name":"Sanat Chandravanshi","link":"https://stackoverflow.com/users/4621980/sanat-chandravanshi"},"is_accepted":false,"score":0,"last_activity_date":1482125657,"creation_date":1482125657,"answer_id":41216294,"question_id":30028697},{"owner":{"reputation":64087,"user_id":2308683,"user_type":"registered","accept_rate":90,"profile_image":"https://www.gravatar.com/avatar/eac16c9fc481cb6825f8b3a35f916b5c?s=128&d=identicon&r=PG","display_name":"cricket_007","link":"https://stackoverflow.com/users/2308683/cricket-007"},"is_accepted":false,"score":2,"last_activity_date":1482131138,"last_edit_date":1482131138,"creation_date":1482125657,"answer_id":41216295,"question_id":41216036},{"owner":{"reputation":1430,"user_id":1349673,"user_type":"registered","accept_rate":33,"profile_image":"https://www.gravatar.com/avatar/e4ee321232e2b4700138d891f6d2f004?s=128&d=identicon&r=PG","display_name":"James Hirschorn","link":"https://stackoverflow.com/users/1349673/james-hirschorn"},"is_accepted":false,"score":3,"last_activity_date":1482125657,"creation_date":1482125657,"answer_id":41216296,"question_id":17818099},{"owner":{"reputation":2017,"user_id":2997855,"user_type":"registered","accept_rate":29,"profile_image":"https://i.stack.imgur.com/KApKI.jpg?s=128&g=1","display_name":"Imran","link":"https://stackoverflow.com/users/2997855/imran"},"is_accepted":false,"score":4,"last_activity_date":1482131386,"last_edit_date":1482131386,"creation_date":1482125682,"answer_id":41216300,"question_id":41216195},{"owner":{"reputation":5068,"user_id":501439,"user_type":"registered","accept_rate":76,"profile_image":"https://i.stack.imgur.com/Vq6Nw.jpg?s=128&g=1","display_name":"GeneCode","link":"https://stackoverflow.com/users/501439/genecode"},"is_accepted":true,"score":0,"last_activity_date":1482125685,"creation_date":1482125685,"answer_id":41216302,"question_id":41216216},{"owner":{"reputation":3202,"user_id":1858330,"user_type":"registered","profile_image":"https://www.gravatar.com/avatar/54e617475b689b28fa9a69151858c601?s=128&d=identicon&r=PG","display_name":"Eugene Shvets - MSFT","link":"https://stackoverflow.com/users/1858330/eugene-shvets-msft"},"is_accepted":true,"score":2,"last_activity_date":1482125692,"creation_date":1482125692,"answer_id":41216303,"question_id":41212467},{"owner":{"reputation":655,"user_id":2855071,"user_type":"registered","accept_rate":73,"profile_image":"https://i.stack.imgur.com/AMDxi.jpg?s=128&g=1","display_name":"innisfree","link":"https://stackoverflow.com/users/2855071/innisfree"},"is_accepted":false,"score":1,"last_activity_date":1482125709,"creation_date":1482125709,"answer_id":41216305,"question_id":41215615},{"owner":{"reputation":10026,"user_id":5447994,"user_type":"registered","accept_rate":67,"profile_image":"https://i.stack.imgur.com/iXbyM.png?s=128&g=1","display_name":"Thamilan","link":"https://stackoverflow.com/users/5447994/thamilan"},"is_accepted":true,"score":1,"last_activity_date":1482125753,"creation_date":1482125753,"answer_id":41216309,"question_id":41216234},{"owner":{"reputation":130,"user_id":1946932,"user_type":"registered","accept_rate":71,"profile_image":"https://www.gravatar.com/avatar/cfd4b894fb15211322b3f810dcf0ef5d?s=128&d=identicon&r=PG","display_name":"user1946932","link":"https://stackoverflow.com/users/1946932/user1946932"},"is_accepted":true,"score":0,"last_activity_date":1482125778,"last_edit_date":1495541635,"creation_date":1482125778,"answer_id":41216314,"question_id":41213069},{"owner":{"reputation":2802,"user_id":5212418,"user_type":"registered","accept_rate":40,"profile_image":"https://i.stack.imgur.com/D6IFM.jpg?s=128&g=1","display_name":"Vasim Vanzara","link":"https://stackoverflow.com/users/5212418/vasim-vanzara"},"is_accepted":false,"score":1,"last_activity_date":1482125809,"creation_date":1482125809,"answer_id":41216315,"question_id":41214433},{"owner":{"reputation":521,"user_id":937464,"user_type":"registered","accept_rate":86,"profile_image":"https://www.gravatar.com/avatar/f4e03d0dc74a5dbf09300a717068ba7b?s=128&d=identicon&r=PG","display_name":"Alice","link":"https://stackoverflow.com/users/937464/alice"},"is_accepted":true,"score":0,"last_activity_date":1482125820,"creation_date":1482125820,"answer_id":41216318,"question_id":41215549},{"owner":{"reputation":36,"user_id":7309423,"user_type":"registered","accept_rate":100,"profile_image":"https://graph.facebook.com/10209622516697582/picture?type=large","display_name":"Mahmoud Magdy Mousaa","link":"https://stackoverflow.com/users/7309423/mahmoud-magdy-mousaa"},"is_accepted":true,"score":0,"last_activity_date":1482128412,"last_edit_date":1482128412,"creation_date":1482125834,"answer_id":41216320,"question_id":41216209},{"owner":{"reputation":303,"user_id":6633352,"user_type":"registered","accept_rate":53,"profile_image":"https://www.gravatar.com/avatar/2e03888b9ace444275cef48b3633b54d?s=128&d=identicon&r=PG&f=1","display_name":"Muju","link":"https://stackoverflow.com/users/6633352/muju"},"is_accepted":true,"score":0,"last_activity_date":1482125837,"creation_date":1482125837,"answer_id":41216321,"question_id":41163456},{"owner":{"reputation":684,"user_id":5172413,"user_type":"registered","accept_rate":100,"profile_image":"https://lh6.googleusercontent.com/-9mUNgJqqNd8/AAAAAAAAAAI/AAAAAAAAABA/HzUqeJud90E/photo.jpg?sz=128","display_name":"Krishna Datt Shukla","link":"https://stackoverflow.com/users/5172413/krishna-datt-shukla"},"is_accepted":true,"score":8,"last_activity_date":1482125857,"creation_date":1482125857,"answer_id":41216325,"question_id":41186802},{"owner":{"reputation":60605,"user_id":256970,"user_type":"registered","accept_rate":86,"profile_image":"https://www.gravatar.com/avatar/87b71ecb90417c88f7873a2f0f9492e9?s=128&d=identicon&r=PG","display_name":"Cary Swoveland","link":"https://stackoverflow.com/users/256970/cary-swoveland"},"is_accepted":false,"score":3,"last_activity_date":1482248766,"last_edit_date":1482248766,"creation_date":1482125858,"answer_id":41216326,"question_id":41213403},{"owner":{"reputation":35700,"user_id":756809,"user_type":"registered","accept_rate":89,"profile_image":"https://i.stack.imgur.com/jFZnE.jpg?s=128&g=1","display_name":"Shai Almog","link":"https://stackoverflow.com/users/756809/shai-almog"},"is_accepted":true,"score":0,"last_activity_date":1482125864,"creation_date":1482125864,"answer_id":41216328,"question_id":41203634},{"owner":{"reputation":11656,"user_id":7005159,"user_type":"registered","profile_image":"https://www.gravatar.com/avatar/550c3427cedf0d13b6d2b03bf25a793f?s=128&d=identicon&r=PG&f=1","display_name":"Tom Sun","link":"https://stackoverflow.com/users/7005159/tom-sun"},"is_accepted":true,"score":1,"last_activity_date":1482199731,"last_edit_date":1482199731,"creation_date":1482125881,"answer_id":41216332,"question_id":41190914},{"owner":{"reputation":142,"user_id":6935752,"user_type":"registered","profile_image":"https://www.gravatar.com/avatar/14135e47b5b3ba0300bbc9b90f17c5fe?s=128&d=identicon&r=PG&f=1","display_name":"Hercules dd","link":"https://stackoverflow.com/users/6935752/hercules-dd"},"is_accepted":false,"score":0,"last_activity_date":1482125883,"creation_date":1482125883,"answer_id":41216333,"question_id":41208473},{"owner":{"reputation":340,"user_id":6348874,"user_type":"registered","accept_rate":100,"profile_image":"https://i.stack.imgur.com/r01ix.png?s=128&g=1","display_name":"Essigwurst","link":"https://stackoverflow.com/users/6348874/essigwurst"},"is_accepted":false,"score":0,"last_activity_date":1482127720,"last_edit_date":1482127720,"creation_date":1482125912,"answer_id":41216335,"question_id":41215872},{"owner":{"reputation":1384,"user_id":1547335,"user_type":"registered","accept_rate":79,"profile_image":"https://www.gravatar.com/avatar/215545e45f92cc8b8e7601305ba5f7d8?s=128&d=identicon&r=PG","display_name":"Alan Wayne","link":"https://stackoverflow.com/users/1547335/alan-wayne"},"is_accepted":false,"score":0,"last_activity_date":1482731680,"last_edit_date":1482731680,"creation_date":1482125915,"answer_id":41216336,"question_id":41212672},{"owner":{"reputation":277,"user_id":7271163,"user_type":"registered","profile_image":"https://i.stack.imgur.com/4tRVG.jpg?s=128&g=1","display_name":"Lalit Dhameliya","link":"https://stackoverflow.com/users/7271163/lalit-dhameliya"},"is_accepted":true,"score":0,"last_activity_date":1482125916,"creation_date":1482125916,"answer_id":41216337,"question_id":41216249},{"owner":{"reputation":93,"user_id":7284069,"user_type":"registered","profile_image":"https://i.stack.imgur.com/qsiWe.jpg?s=128&g=1","display_name":"Mahesh","link":"https://stackoverflow.com/users/7284069/mahesh"},"is_accepted":false,"score":1,"last_activity_date":1482125959,"creation_date":1482125959,"answer_id":41216339,"question_id":41216232},{"owner":{"reputation":111807,"user_id":1668533,"user_type":"registered","profile_image":"https://i.stack.imgur.com/EUNRw.jpg?s=128&g=1","display_name":"Satpal","link":"https://stackoverflow.com/users/1668533/satpal"},"is_accepted":true,"score":3,"last_activity_date":1482125970,"creation_date":1482125970,"answer_id":41216342,"question_id":41216324},{"owner":{"reputation":7979,"user_id":5620055,"user_type":"registered","profile_image":"https://i.stack.imgur.com/7e3M5.jpg?s=128&g=1","display_name":"Sunteen Wu - MSFT","link":"https://stackoverflow.com/users/5620055/sunteen-wu-msft"},"is_accepted":false,"score":0,"last_activity_date":1482125977,"creation_date":1482125977,"answer_id":41216345,"question_id":41198413},{"owner":{"reputation":1,"user_id":2801559,"user_type":"registered","accept_rate":74,"profile_image":"https://www.gravatar.com/avatar/9538ef609067e6d6a842dfef189b77d2?s=128&d=identicon&r=PG","display_name":"guest271314","link":"https://stackoverflow.com/users/2801559/guest271314"},"is_accepted":false,"score":1,"last_activity_date":1482126003,"creation_date":1482126003,"answer_id":41216350,"question_id":41216222},{"owner":{"reputation":24613,"user_id":1906356,"user_type":"registered","profile_image":"https://lh4.googleusercontent.com/-nOR-lGSM4OQ/AAAAAAAAAAI/AAAAAAAAAKc/JK3VzYOOB-I/photo.jpg?sz=128","display_name":"madalinivascu","link":"https://stackoverflow.com/users/1906356/madalinivascu"},"is_accepted":false,"score":1,"last_activity_date":1482126577,"last_edit_date":1482126577,"creation_date":1482126018,"answer_id":41216352,"question_id":41216324},{"owner":{"reputation":368,"user_id":5184462,"user_type":"registered","accept_rate":80,"profile_image":"https://i.stack.imgur.com/a6Z0v.jpg?s=128&g=1","display_name":"Jordan","link":"https://stackoverflow.com/users/5184462/jordan"},"is_accepted":false,"score":0,"last_activity_date":1482126019,"creation_date":1482126019,"answer_id":41216353,"question_id":41216249},{"owner":{"reputation":999,"user_id":5262399,"user_type":"registered","profile_image":"https://www.gravatar.com/avatar/311e295cc6f280e6ca1dfe84ad76db16?s=128&d=identicon&r=PG&f=1","display_name":"Russell Sim","link":"https://stackoverflow.com/users/5262399/russell-sim"},"is_accepted":false,"score":0,"last_activity_date":1482126021,"creation_date":1482126021,"answer_id":41216354,"question_id":41216323},{"owner":{"reputation":3274,"user_id":2526525,"user_type":"registered","profile_image":"https://i.stack.imgur.com/geyVo.jpg?s=128&g=1","display_name":"partypete25","link":"https://stackoverflow.com/users/2526525/partypete25"},"is_accepted":false,"score":0,"last_activity_date":1482126025,"creation_date":1482126025,"answer_id":41216356,"question_id":41214973},{"owner":{"reputation":14089,"user_id":4787126,"user_type":"registered","profile_image":"https://www.gravatar.com/avatar/2a822df86c907c77c792a8f91b2bab41?s=128&d=identicon&r=PG&f=1","display_name":"Zbynek Vyskovsky - kvr000","link":"https://stackoverflow.com/users/4787126/zbynek-vyskovsky-kvr000"},"is_accepted":false,"score":3,"last_activity_date":1482126028,"creation_date":1482126028,"answer_id":41216357,"question_id":41216188}]