[{"owner":{"reputation":180080,"user_id":10397,"user_type":"registered","profile_image":"https://www.gravatar.com/avatar/0a116491222bf3f94c85381528593fd7?s=128&d=identicon&r=PG","display_name":"Justin Cave","link":"https://stackoverflow.com/users/10397/justin-cave"},"is_accepted":false,"score":0,"last_activity_date":1480561486,"creation_date":1480561486,"answer_id":40901956,"question_id":40901116},{"owner":{"reputation":249350,"user_id":589924,"user_type":"registered","accept_rate":100,"profile_image":"https://www.gravatar.com/avatar/b2cf53d5a3d25f95c0db4e025aed4153?s=128&d=identicon&r=PG","display_name":"ikegami","link":"https://stackoverflow.com/users/589924/ikegami"},"is_accepted":false,"score":7,"last_activity_date":1480617248,"last_edit_date":1480617248,"creation_date":1480561492,"answer_id":40901957,"question_id":40900584},{"owner":{"reputation":1109,"user_id":1553510,"user_type":"registered","accept_rate":43,"profile_image":"https://www.gravatar.com/avatar/06dc19d698f7ea0a429558bacc595a87?s=128&d=identicon&r=PG","display_name":"F0r3v3r-A-N00b","link":"https://stackoverflow.com/users/1553510/f0r3v3r-a-n00b"},"is_accepted":false,"score":0,"last_activity_date":1480569597,"last_edit_date":1480569597,"creation_date":1480561507,"answer_id":40901959,"question_id":40901583},{"owner":{"reputation":432,"user_id":1373369,"user_type":"registered","accept_rate":61,"profile_image":"https://i.stack.imgur.com/ss4d2.png?s=128&g=1","display_name":"Bakri","link":"https://stackoverflow.com/users/1373369/bakri"},"is_accepted":false,"score":0,"last_activity_date":1480561542,"creation_date":1480561542,"answer_id":40901963,"question_id":40901769},{"owner":{"reputation":53173,"user_id":1766831,"user_type":"registered","profile_image":"https://www.gravatar.com/avatar/1ee974306d2def46eb69534fbcf95cc5?s=128&d=identicon&r=PG","display_name":"Rick James","link":"https://stackoverflow.com/users/1766831/rick-james"},"is_accepted":true,"score":1,"last_activity_date":1480561550,"creation_date":1480561550,"answer_id":40901964,"question_id":40891532},{"owner":{"reputation":643,"user_id":1870884,"user_type":"registered","profile_image":"https://www.gravatar.com/avatar/83e51a8c35a72ac3b62382093da1b295?s=128&d=identicon&r=PG","display_name":"Tina","link":"https://stackoverflow.com/users/1870884/tina"},"is_accepted":true,"score":2,"last_activity_date":1480562773,"last_edit_date":1480562773,"creation_date":1480561582,"answer_id":40901967,"question_id":40901555},{"owner":{"reputation":10265,"user_id":5752362,"user_type":"registered","profile_image":"https://i.stack.imgur.com/fHSfj.jpg?s=128&g=1","display_name":"Fei Xue","link":"https://stackoverflow.com/users/5752362/fei-xue"},"is_accepted":false,"score":0,"last_activity_date":1480561586,"creation_date":1480561586,"answer_id":40901972,"question_id":40893657},{"owner":{"reputation":1746,"user_id":2329487,"user_type":"registered","profile_image":"https://www.gravatar.com/avatar/8912a5e80f46448c3918c201d6b67f43?s=128&d=identicon&r=PG","display_name":"shudder","link":"https://stackoverflow.com/users/2329487/shudder"},"is_accepted":false,"score":0,"last_activity_date":1480626814,"last_edit_date":1495540906,"creation_date":1480561590,"answer_id":40901970,"question_id":40901068},{"owner":{"reputation":9490,"user_id":590203,"user_type":"registered","accept_rate":83,"profile_image":"https://i.stack.imgur.com/zKAYQ.jpg?s=128&g=1","display_name":"Josh Rosen","link":"https://stackoverflow.com/users/590203/josh-rosen"},"is_accepted":true,"score":2,"last_activity_date":1480561634,"creation_date":1480561634,"answer_id":40901975,"question_id":40901636},{"owner":{"reputation":1642,"user_id":2065333,"user_type":"registered","profile_image":"https://www.gravatar.com/avatar/7766a73bbc629c57f8079e7e6d99b06b?s=128&d=identicon&r=PG","display_name":"Bob Dust","link":"https://stackoverflow.com/users/2065333/bob-dust"},"is_accepted":false,"score":0,"last_activity_date":1480561646,"creation_date":1480561646,"answer_id":40901979,"question_id":40882466},{"owner":{"reputation":56,"user_id":6819074,"user_type":"registered","profile_image":"https://lh6.googleusercontent.com/-zAGxYUs39ss/AAAAAAAAAAI/AAAAAAAAABQ/xJeZgMcsqlc/photo.jpg?sz=128","display_name":"darkThanBlack","link":"https://stackoverflow.com/users/6819074/darkthanblack"},"is_accepted":false,"score":1,"last_activity_date":1480561660,"creation_date":1480561660,"answer_id":40901980,"question_id":40901684},{"owner":{"reputation":1078,"user_id":3627358,"user_type":"registered","accept_rate":69,"profile_image":"https://i.stack.imgur.com/sfl8m.jpg?s=128&g=1","display_name":"RainCast","link":"https://stackoverflow.com/users/3627358/raincast"},"is_accepted":false,"score":0,"last_activity_date":1480561667,"creation_date":1480561667,"answer_id":40901981,"question_id":8661181},{"owner":{"reputation":54694,"user_id":5768908,"user_type":"registered","accept_rate":100,"profile_image":"https://i.stack.imgur.com/PjGM7.jpg?s=128&g=1","display_name":"Gerardo Furtado","link":"https://stackoverflow.com/users/5768908/gerardo-furtado"},"is_accepted":false,"score":0,"last_activity_date":1480562074,"last_edit_date":1480562074,"creation_date":1480561688,"answer_id":40901984,"question_id":40895367},{"owner":{"reputation":2985,"user_id":26167,"user_type":"registered","accept_rate":80,"profile_image":"https://www.gravatar.com/avatar/56dd20706066ea345b2f02759ef6c453?s=128&d=identicon&r=PG","display_name":"piers7","link":"https://stackoverflow.com/users/26167/piers7"},"is_accepted":false,"score":2,"last_activity_date":1480561691,"last_edit_date":1495539984,"creation_date":1480561691,"answer_id":40901985,"question_id":19646581},{"owner":{"reputation":136,"user_id":2434608,"user_type":"registered","accept_rate":70,"profile_image":"https://www.gravatar.com/avatar/be1a75afcecaa4cead925f984d49d3ae?s=128&d=identicon&r=PG","display_name":"AshD","link":"https://stackoverflow.com/users/2434608/ashd"},"is_accepted":true,"score":0,"last_activity_date":1480561695,"creation_date":1480561695,"answer_id":40901986,"question_id":40736419},{"owner":{"reputation":3472,"user_id":5055063,"user_type":"registered","accept_rate":100,"profile_image":"https://i.stack.imgur.com/ppjHO.jpg?s=128&g=1","display_name":"Nick Zuber","link":"https://stackoverflow.com/users/5055063/nick-zuber"},"is_accepted":false,"score":0,"last_activity_date":1480562952,"last_edit_date":1495541634,"creation_date":1480561715,"answer_id":40901989,"question_id":40901907},{"owner":{"reputation":19705,"user_id":2813224,"user_type":"registered","accept_rate":100,"profile_image":"https://i.stack.imgur.com/aekfP.png?s=128&g=1","display_name":"zer00ne","link":"https://stackoverflow.com/users/2813224/zer00ne"},"is_accepted":true,"score":0,"last_activity_date":1481396880,"last_edit_date":1481396880,"creation_date":1480561717,"answer_id":40901990,"question_id":40897482},{"owner":{"reputation":13431,"user_id":3282056,"user_type":"registered","accept_rate":80,"profile_image":"https://i.stack.imgur.com/IXonK.jpg?s=128&g=1","display_name":"rcgldr","link":"https://stackoverflow.com/users/3282056/rcgldr"},"is_accepted":true,"score":0,"last_activity_date":1480656912,"last_edit_date":1480656912,"creation_date":1480561732,"answer_id":40901991,"question_id":40901768},{"owner":{"reputation":1515,"user_id":225134,"user_type":"registered","accept_rate":73,"profile_image":"https://www.gravatar.com/avatar/d95941e31033a751adae892fd710992e?s=128&d=identicon&r=PG","display_name":"fredrover","link":"https://stackoverflow.com/users/225134/fredrover"},"is_accepted":false,"score":2,"last_activity_date":1480562386,"last_edit_date":1480562386,"creation_date":1480561739,"answer_id":40901995,"question_id":40901555},{"owner":{"reputation":1806,"user_id":364474,"user_type":"registered","accept_rate":31,"profile_image":"https://i.stack.imgur.com/VB0a4.png?s=128&g=1","display_name":"learningloop","link":"https://stackoverflow.com/users/364474/learningloop"},"is_accepted":true,"score":1,"last_activity_date":1480561740,"creation_date":1480561740,"answer_id":40901996,"question_id":40895846},{"owner":{"reputation":72,"user_id":2334001,"user_type":"registered","accept_rate":69,"profile_image":"https://i.stack.imgur.com/d7QeA.jpg?s=128&g=1","display_name":"Minum","link":"https://stackoverflow.com/users/2334001/minum"},"is_accepted":true,"score":1,"last_activity_date":1480561742,"creation_date":1480561742,"answer_id":40901997,"question_id":40901812},{"owner":{"reputation":341,"user_id":7033422,"user_type":"registered","accept_rate":23,"profile_image":"https://i.stack.imgur.com/6Zyg5.png?s=128&g=1","display_name":"Ira","link":"https://stackoverflow.com/users/7033422/ira"},"is_accepted":false,"score":0,"last_activity_date":1480561764,"creation_date":1480561764,"answer_id":40902002,"question_id":40848995},{"owner":{"reputation":21,"user_id":7234138,"user_type":"registered","profile_image":"https://lh6.googleusercontent.com/-Vg3Q_K8BAsc/AAAAAAAAAAI/AAAAAAAACU0/J7k050T3SrI/photo.jpg?sz=128","display_name":"Biswanath Roy","link":"https://stackoverflow.com/users/7234138/biswanath-roy"},"is_accepted":false,"score":2,"last_activity_date":1480576852,"last_edit_date":1480576852,"creation_date":1480561776,"answer_id":40902004,"question_id":33559733},{"owner":{"reputation":3847,"user_id":6601554,"user_type":"registered","profile_image":"https://www.gravatar.com/avatar/a9d8e70907365c8fce9135ffe1e5868f?s=128&d=identicon&r=PG&f=1","display_name":"Jack Zhai-MSFT","link":"https://stackoverflow.com/users/6601554/jack-zhai-msft"},"is_accepted":false,"score":1,"last_activity_date":1480561800,"creation_date":1480561800,"answer_id":40902010,"question_id":40892834},{"owner":{"reputation":4418,"user_id":1119381,"user_type":"registered","accept_rate":61,"profile_image":"https://www.gravatar.com/avatar/aab36e75e2a1b09199da99501429f49e?s=128&d=identicon&r=PG","display_name":"Eugene S","link":"https://stackoverflow.com/users/1119381/eugene-s"},"is_accepted":true,"score":2,"last_activity_date":1480561842,"creation_date":1480561842,"answer_id":40902012,"question_id":40901267},{"owner":{"reputation":6717,"user_id":126027,"user_type":"registered","profile_image":"https://www.gravatar.com/avatar/d083341daacfb4942b835e3f6f2fd804?s=128&d=identicon&r=PG","display_name":"TheUndeadFish","link":"https://stackoverflow.com/users/126027/theundeadfish"},"is_accepted":true,"score":2,"last_activity_date":1480561862,"creation_date":1480561862,"answer_id":40902014,"question_id":40901869},{"owner":{"reputation":522,"user_id":7232773,"user_type":"registered","profile_image":"https://i.stack.imgur.com/jpoaF.jpg?s=128&g=1","display_name":"M. Davis","link":"https://stackoverflow.com/users/7232773/m-davis"},"is_accepted":false,"score":0,"last_activity_date":1480561863,"creation_date":1480561863,"answer_id":40902015,"question_id":40901693},{"owner":{"reputation":34,"user_id":7203341,"user_type":"registered","profile_image":"https://lh4.googleusercontent.com/-dwQNaBoagW4/AAAAAAAAAAI/AAAAAAAAIPU/Raua0c_lrCc/photo.jpg?sz=128","display_name":"Shalaka Deshpande","link":"https://stackoverflow.com/users/7203341/shalaka-deshpande"},"is_accepted":false,"score":2,"last_activity_date":1480563160,"last_edit_date":1480563160,"creation_date":1480561869,"answer_id":40902016,"question_id":36792681},{"owner":{"reputation":263380,"user_id":131872,"user_type":"registered","accept_rate":100,"profile_image":"https://www.gravatar.com/avatar/a0ced8e21d2a761db718acb6362b9225?s=128&d=identicon&r=PG","display_name":"camickr","link":"https://stackoverflow.com/users/131872/camickr"},"is_accepted":true,"score":1,"last_activity_date":1480561875,"creation_date":1480561875,"answer_id":40902017,"question_id":40901128},{"owner":{"reputation":22025,"user_id":1610034,"user_type":"registered","accept_rate":55,"profile_image":"https://i.stack.imgur.com/x77Vf.jpg?s=128&g=1","display_name":"Saurabh","link":"https://stackoverflow.com/users/1610034/saurabh"},"is_accepted":true,"score":2,"last_activity_date":1480561888,"creation_date":1480561888,"answer_id":40902019,"question_id":40901552}]