[{"owner":{"reputation":2857,"user_id":1090791,"user_type":"registered","accept_rate":63,"profile_image":"https://i.stack.imgur.com/Ls3wG.png?s=128&g=1","display_name":"gzc","link":"https://stackoverflow.com/users/1090791/gzc"},"is_accepted":false,"score":1,"last_activity_date":1482079875,"creation_date":1482079875,"answer_id":41210648,"question_id":41210562},{"owner":{"reputation":136,"user_id":5221355,"user_type":"registered","profile_image":"https://www.gravatar.com/avatar/95e9addd5e6367a379d073e9a501b259?s=128&d=identicon&r=PG","display_name":"guilherme.oc97","link":"https://stackoverflow.com/users/5221355/guilherme-oc97"},"is_accepted":true,"score":0,"last_activity_date":1482079876,"creation_date":1482079876,"answer_id":41210649,"question_id":41210422},{"owner":{"reputation":17331,"user_id":380384,"user_type":"registered","accept_rate":92,"profile_image":"https://i.stack.imgur.com/848A1.png?s=128&g=1","display_name":"ja72","link":"https://stackoverflow.com/users/380384/ja72"},"is_accepted":true,"score":1,"last_activity_date":1482079881,"creation_date":1482079881,"answer_id":41210650,"question_id":41185375},{"owner":{"reputation":8318,"user_id":1730261,"user_type":"registered","accept_rate":86,"profile_image":"https://i.stack.imgur.com/m57hO.jpg?s=128&g=1","display_name":"Rushy Panchal","link":"https://stackoverflow.com/users/1730261/rushy-panchal"},"is_accepted":false,"score":0,"last_activity_date":1482079885,"creation_date":1482079885,"answer_id":41210651,"question_id":41210596},{"owner":{"reputation":16289,"user_id":6139861,"user_type":"registered","profile_image":"https://i.stack.imgur.com/HBFV4.jpg?s=128&g=1","display_name":"rafsanahmad007","link":"https://stackoverflow.com/users/6139861/rafsanahmad007"},"is_accepted":true,"score":0,"last_activity_date":1482079890,"creation_date":1482079890,"answer_id":41210653,"question_id":41209487},{"owner":{"reputation":614,"user_id":5278483,"user_type":"registered","accept_rate":75,"profile_image":"https://i.stack.imgur.com/bxseR.jpg?s=128&g=1","display_name":"Abdelhakim Akodadi","link":"https://stackoverflow.com/users/5278483/abdelhakim-akodadi"},"is_accepted":false,"score":1,"last_activity_date":1482079904,"creation_date":1482079904,"answer_id":41210654,"question_id":41210198},{"owner":{"reputation":54027,"user_id":168986,"user_type":"registered","accept_rate":86,"profile_image":"https://i.stack.imgur.com/MqorX.jpg?s=128&g=1","display_name":"Clifford","link":"https://stackoverflow.com/users/168986/clifford"},"is_accepted":true,"score":0,"last_activity_date":1482134317,"last_edit_date":1482134317,"creation_date":1482079923,"answer_id":41210655,"question_id":41210227},{"owner":{"reputation":16092,"user_id":16800,"user_type":"registered","profile_image":"https://www.gravatar.com/avatar/ea1de76c4c343fc844135e18da8a80f1?s=128&d=identicon&r=PG","display_name":"Guvante","link":"https://stackoverflow.com/users/16800/guvante"},"is_accepted":false,"score":0,"last_activity_date":1482079948,"creation_date":1482079948,"answer_id":41210658,"question_id":41210598},{"owner":{"reputation":49213,"user_id":380231,"user_type":"registered","accept_rate":100,"profile_image":"https://www.gravatar.com/avatar/8744048060e5931c500d3c9d1ecb997e?s=128&d=identicon&r=PG","display_name":"tacaswell","link":"https://stackoverflow.com/users/380231/tacaswell"},"is_accepted":false,"score":0,"last_activity_date":1482079982,"creation_date":1482079982,"answer_id":41210664,"question_id":35829961},{"owner":{"reputation":197,"user_id":2418640,"user_type":"registered","accept_rate":50,"profile_image":"https://www.gravatar.com/avatar/06718c0a4c2419842de27983b65f2c64?s=128&d=identicon&r=PG","display_name":"khetanrajesh","link":"https://stackoverflow.com/users/2418640/khetanrajesh"},"is_accepted":true,"score":1,"last_activity_date":1482080000,"creation_date":1482080000,"answer_id":41210668,"question_id":41210481},{"owner":{"reputation":1985,"user_id":6354622,"user_type":"registered","accept_rate":76,"profile_image":"https://i.stack.imgur.com/rNoam.jpg?s=128&g=1","display_name":"User_Targaryen","link":"https://stackoverflow.com/users/6354622/user-targaryen"},"is_accepted":true,"score":0,"last_activity_date":1482080001,"last_edit_date":1495542290,"creation_date":1482080001,"answer_id":41210670,"question_id":41210309},{"owner":{"reputation":1,"user_id":3235357,"user_type":"registered","profile_image":"https://www.gravatar.com/avatar/4470ce4cc6e904969b98378ce70e6305?s=128&d=identicon&r=PG&f=1","display_name":"user3235357","link":"https://stackoverflow.com/users/3235357/user3235357"},"is_accepted":false,"score":0,"last_activity_date":1482080020,"creation_date":1482080020,"answer_id":41210674,"question_id":30928203},{"owner":{"reputation":841,"user_id":1635042,"user_type":"registered","profile_image":"https://i.stack.imgur.com/PsAEm.jpg?s=128&g=1","display_name":"Mete Cantimur","link":"https://stackoverflow.com/users/1635042/mete-cantimur"},"is_accepted":true,"score":1,"last_activity_date":1482080444,"last_edit_date":1482080444,"creation_date":1482080058,"answer_id":41210679,"question_id":41170835},{"owner":{"reputation":121,"user_id":7119946,"user_type":"registered","profile_image":"https://www.gravatar.com/avatar/ba29ff584233c0be4da34a1bce5d1322?s=128&d=identicon&r=PG&f=1","display_name":"snagpaul","link":"https://stackoverflow.com/users/7119946/snagpaul"},"is_accepted":false,"score":12,"last_activity_date":1482080059,"creation_date":1482080059,"answer_id":41210681,"question_id":56860},{"owner":{"reputation":401,"user_id":1421378,"user_type":"registered","accept_rate":41,"profile_image":"https://www.gravatar.com/avatar/850d60ee8959d99c63209671bba7a0c1?s=128&d=identicon&r=PG&f=1","display_name":"Markus","link":"https://stackoverflow.com/users/1421378/markus"},"is_accepted":false,"score":2,"last_activity_date":1482080068,"creation_date":1482080068,"answer_id":41210683,"question_id":30483276},{"owner":{"reputation":247,"user_id":4402190,"user_type":"registered","accept_rate":71,"profile_image":"https://www.gravatar.com/avatar/749c7c96c5c749db724457d295747c2e?s=128&d=identicon&r=PG&f=1","display_name":"Danielius","link":"https://stackoverflow.com/users/4402190/danielius"},"is_accepted":false,"score":0,"last_activity_date":1482080083,"creation_date":1482080083,"answer_id":41210686,"question_id":41210401},{"owner":{"reputation":17,"user_id":4796983,"user_type":"registered","accept_rate":75,"profile_image":"https://i.stack.imgur.com/OaRkx.jpg?s=128&g=1","display_name":"Sina M.Azad","link":"https://stackoverflow.com/users/4796983/sina-m-azad"},"is_accepted":false,"score":0,"last_activity_date":1482084958,"last_edit_date":1482084958,"creation_date":1482080120,"answer_id":41210689,"question_id":41210569},{"owner":{"reputation":174,"user_id":6341735,"user_type":"registered","accept_rate":82,"profile_image":"https://www.gravatar.com/avatar/cca89baee9280d5d9a2bb812e23e1f22?s=128&d=identicon&r=PG&f=1","display_name":"pwnz22","link":"https://stackoverflow.com/users/6341735/pwnz22"},"is_accepted":true,"score":0,"last_activity_date":1482080144,"creation_date":1482080144,"answer_id":41210692,"question_id":41210574},{"owner":{"reputation":6,"user_id":7190448,"user_type":"registered","profile_image":"https://www.gravatar.com/avatar/51e06daedb5a3f4c834f8bb402339d48?s=128&d=identicon&r=PG&f=1","display_name":"user7190448","link":"https://stackoverflow.com/users/7190448/user7190448"},"is_accepted":false,"score":0,"last_activity_date":1482080145,"creation_date":1482080145,"answer_id":41210693,"question_id":40725573},{"owner":{"reputation":825,"user_id":4698546,"user_type":"registered","profile_image":"https://i.stack.imgur.com/VdAiN.jpg?s=128&g=1","display_name":"bugfroggy","link":"https://stackoverflow.com/users/4698546/bugfroggy"},"is_accepted":false,"score":0,"last_activity_date":1482080201,"creation_date":1482080201,"answer_id":41210697,"question_id":41210362},{"owner":{"reputation":985,"user_id":3760021,"user_type":"registered","accept_rate":17,"profile_image":"https://graph.facebook.com/1168165975/picture?type=large","display_name":"RafaelCaballero","link":"https://stackoverflow.com/users/3760021/rafaelcaballero"},"is_accepted":false,"score":0,"last_activity_date":1482080216,"creation_date":1482080216,"answer_id":41210699,"question_id":41209256},{"owner":{"reputation":4458,"user_id":793861,"user_type":"registered","accept_rate":50,"profile_image":"https://i.stack.imgur.com/GBxXg.jpg?s=128&g=1","display_name":"John O&#39;Reilly","link":"https://stackoverflow.com/users/793861/john-oreilly"},"is_accepted":false,"score":0,"last_activity_date":1482080218,"creation_date":1482080218,"answer_id":41210700,"question_id":41210685},{"owner":{"reputation":447,"user_id":4278899,"user_type":"registered","profile_image":"https://www.gravatar.com/avatar/af3913481d8a368cdf8f58832c2222bb?s=128&d=identicon&r=PG","display_name":"Olivier Meurice","link":"https://stackoverflow.com/users/4278899/olivier-meurice"},"is_accepted":false,"score":1,"last_activity_date":1482080267,"creation_date":1482080267,"answer_id":41210706,"question_id":41210369},{"owner":{"reputation":1993,"user_id":5735010,"user_type":"registered","accept_rate":70,"profile_image":"https://i.stack.imgur.com/znAEN.jpg?s=128&g=1","display_name":"abhiarora","link":"https://stackoverflow.com/users/5735010/abhiarora"},"is_accepted":true,"score":2,"last_activity_date":1482080282,"creation_date":1482080282,"answer_id":41210708,"question_id":41210596},{"owner":{"reputation":44,"user_id":1506226,"user_type":"registered","accept_rate":0,"profile_image":"https://www.gravatar.com/avatar/6b57e8cc6336f4828ec4222281b8c741?s=128&d=identicon&r=PG","display_name":"zmau","link":"https://stackoverflow.com/users/1506226/zmau"},"is_accepted":false,"score":0,"last_activity_date":1482080293,"creation_date":1482080293,"answer_id":41210709,"question_id":41192838},{"owner":{"reputation":39935,"user_id":1832058,"user_type":"registered","profile_image":"https://i.stack.imgur.com/relWs.jpg?s=128&g=1","display_name":"furas","link":"https://stackoverflow.com/users/1832058/furas"},"is_accepted":true,"score":1,"last_activity_date":1482081720,"last_edit_date":1482081720,"creation_date":1482080319,"answer_id":41210712,"question_id":41210188},{"owner":{"reputation":694,"user_id":238831,"user_type":"registered","accept_rate":71,"profile_image":"https://graph.facebook.com/100002472845215/picture?type=large","display_name":"Ginger Opariti","link":"https://stackoverflow.com/users/238831/ginger-opariti"},"is_accepted":true,"score":1,"last_activity_date":1482083731,"last_edit_date":1482083731,"creation_date":1482080323,"answer_id":41210713,"question_id":41199322},{"owner":{"reputation":722672,"user_id":115145,"user_type":"registered","accept_rate":84,"profile_image":"https://i.stack.imgur.com/wDnd8.png?s=128&g=1","display_name":"CommonsWare","link":"https://stackoverflow.com/users/115145/commonsware"},"is_accepted":true,"score":5,"last_activity_date":1482080348,"creation_date":1482080348,"answer_id":41210717,"question_id":41210659},{"owner":{"reputation":134335,"user_id":2587435,"user_type":"registered","accept_rate":88,"profile_image":"https://i.stack.imgur.com/w9jTN.jpg?s=128&g=1","display_name":"Paul Samsotha","link":"https://stackoverflow.com/users/2587435/paul-samsotha"},"is_accepted":true,"score":2,"last_activity_date":1482082697,"last_edit_date":1482082697,"creation_date":1482080357,"answer_id":41210719,"question_id":41210367},{"owner":{"reputation":199,"user_id":2153296,"user_type":"registered","profile_image":"https://www.gravatar.com/avatar/e61814dcaccd48123b03c0edebbcbbcc?s=128&d=identicon&r=PG","display_name":"puritys","link":"https://stackoverflow.com/users/2153296/puritys"},"is_accepted":true,"score":2,"last_activity_date":1482081599,"last_edit_date":1482081599,"creation_date":1482080368,"answer_id":41210720,"question_id":41141644}]