[{"tags":["java","collections"],"owner":{"reputation":3,"user_id":6769450,"user_type":"registered","profile_image":"https://www.gravatar.com/avatar/662d760846fef87dae87c595e526d13b?s=128&d=identicon&r=PG&f=1","display_name":"Ололош Ололоев","link":"https://stackoverflow.com/users/6769450/%d0%9e%d0%bb%d0%be%d0%bb%d0%be%d1%88-%d0%9e%d0%bb%d0%be%d0%bb%d0%be%d0%b5%d0%b2"},"is_answered":true,"view_count":148,"closed_date":1482070752,"accepted_answer_id":41209169,"answer_count":1,"score":-5,"last_activity_date":1482159514,"creation_date":1482068838,"last_edit_date":1482159514,"question_id":41208940,"link":"https://stackoverflow.com/questions/41208940/how-do-i-convert-a-set-into-2d-array-in-java","closed_reason":"too broad","title":"How do i convert a Set into 2D array in java?"},{"tags":["python","python-3.x","diagnostics"],"owner":{"reputation":2,"user_id":7303550,"user_type":"registered","profile_image":"https://www.gravatar.com/avatar/36e86306b0c98e01617769b1f47d6699?s=128&d=identicon&r=PG&f=1","display_name":"mr.python","link":"https://stackoverflow.com/users/7303550/mr-python"},"is_answered":true,"view_count":23,"answer_count":1,"score":-1,"last_activity_date":1482069680,"creation_date":1482068847,"question_id":41208942,"link":"https://stackoverflow.com/questions/41208942/importing-and-exporting-to-a-text-file-python","title":"Importing and exporting to a text file - Python"},{"tags":["angularjs","requirejs","angular-routing","route-provider"],"owner":{"reputation":640,"user_id":3041058,"user_type":"registered","accept_rate":96,"profile_image":"https://www.gravatar.com/avatar/834da9e46958a628bc3d9661963d8f7e?s=128&d=identicon&r=PG&f=1","display_name":"user3041058","link":"https://stackoverflow.com/users/3041058/user3041058"},"is_answered":false,"view_count":50,"answer_count":0,"score":1,"last_activity_date":1485836029,"creation_date":1482068848,"question_id":41208944,"link":"https://stackoverflow.com/questions/41208944/angular-rotue-provider-not-working-with-require-js","title":"Angular rotue provider not working with Require JS"},{"tags":["php","windows","active-directory","ldap","mediawiki"],"owner":{"reputation":3580,"user_id":1657610,"user_type":"registered","accept_rate":70,"profile_image":"https://i.stack.imgur.com/kcTi0.png?s=128&g=1","display_name":"Reg Edit","link":"https://stackoverflow.com/users/1657610/reg-edit"},"is_answered":false,"view_count":97,"answer_count":0,"score":1,"last_activity_date":1482075706,"creation_date":1482068865,"last_edit_date":1482075706,"question_id":41208947,"link":"https://stackoverflow.com/questions/41208947/php-ldap-authenticates-on-ad-domain-fails-on-second-ad-domain-with-incorrect-p","title":"PHP LDAP authenticates on AD domain, fails on second AD domain with &quot;Incorrect password&quot;. (Using MediaWiki LDAP extension)"},{"tags":["uitextfield","swift3","xcode8","inputaccessoryview","unusernotificationcenter"],"owner":{"reputation":136,"user_id":4549677,"user_type":"registered","accept_rate":75,"profile_image":"https://graph.facebook.com/10152565221337447/picture?type=large","display_name":"Apoorv Mote","link":"https://stackoverflow.com/users/4549677/apoorv-mote"},"is_answered":true,"view_count":286,"answer_count":1,"score":2,"last_activity_date":1493282649,"creation_date":1482068867,"question_id":41208948,"link":"https://stackoverflow.com/questions/41208948/custom-input-accessory-view-notification","title":"Custom input accessory view Notification"},{"tags":["wso2","siddhi"],"owner":{"reputation":6,"user_id":7312960,"user_type":"registered","profile_image":"https://www.gravatar.com/avatar/9b1fa8ef282330660d7d9779fa5650b5?s=128&d=identicon&r=PG&f=1","display_name":"zuoxb","link":"https://stackoverflow.com/users/7312960/zuoxb"},"is_answered":true,"view_count":84,"accepted_answer_id":41214853,"answer_count":1,"score":0,"last_activity_date":1482112782,"creation_date":1482068894,"last_edit_date":1482070381,"question_id":41208952,"link":"https://stackoverflow.com/questions/41208952/how-can-i-use-wso2-siddhiql-cache-data","title":"how can i use wso2 siddhiQL Cache data?"},{"tags":["python","string","shell","command","output"],"owner":{"reputation":133,"user_id":2868984,"user_type":"registered","accept_rate":86,"profile_image":"https://www.gravatar.com/avatar/2f8d4e85b75ef5fadf30c9dc62bbee10?s=128&d=identicon&r=PG&f=1","display_name":"Wildan Maulana Syahidillah","link":"https://stackoverflow.com/users/2868984/wildan-maulana-syahidillah"},"is_answered":false,"view_count":61,"answer_count":1,"score":-1,"last_activity_date":1482931034,"creation_date":1482068898,"last_edit_date":1482083335,"question_id":41208953,"link":"https://stackoverflow.com/questions/41208953/how-to-run-this-multicommand-shell-with-in-python","title":"How to run this multicommand shell with &quot;|&quot; in python"},{"tags":["php","mysql"],"owner":{"reputation":31,"user_id":2625741,"user_type":"registered","accept_rate":12,"profile_image":"https://graph.facebook.com/100001202200169/picture?type=large","display_name":"Parvinder Singh","link":"https://stackoverflow.com/users/2625741/parvinder-singh"},"is_answered":true,"view_count":48,"answer_count":2,"score":0,"last_activity_date":1482069862,"creation_date":1482068904,"question_id":41208954,"link":"https://stackoverflow.com/questions/41208954/how-to-get-number-of-results-by-using-file-get-contents","title":"How to get number of results by using file_get_contents"},{"tags":["javascript","html","external"],"owner":{"reputation":3,"user_id":7280582,"user_type":"registered","profile_image":"https://lh6.googleusercontent.com/-ZKw9oTpJ7U8/AAAAAAAAAAI/AAAAAAAAAMo/0h9GtoIJdXw/photo.jpg?sz=128","display_name":"ProgrammingNinja","link":"https://stackoverflow.com/users/7280582/programmingninja"},"is_answered":true,"view_count":88,"closed_date":1482110640,"accepted_answer_id":41209148,"answer_count":1,"score":-5,"last_activity_date":1482072143,"creation_date":1482068940,"last_edit_date":1482072143,"question_id":41208959,"link":"https://stackoverflow.com/questions/41208959/why-would-an-external-script-file-be-used-as-an-alternative-to-an-embedded-scrip","closed_reason":"duplicate","title":"why would an external script file be used as an alternative to an embedded script file?"},{"tags":["c","linux","memory-management","malloc","heap"],"owner":{"reputation":112,"user_id":6183919,"user_type":"registered","accept_rate":86,"profile_image":"https://www.gravatar.com/avatar/ea958eebda31fa83b6a61fd373abc37c?s=128&d=identicon&r=PG&f=1","display_name":"Dennis","link":"https://stackoverflow.com/users/6183919/dennis"},"is_answered":true,"view_count":181,"accepted_answer_id":41209582,"answer_count":1,"score":5,"last_activity_date":1482072910,"creation_date":1482069014,"question_id":41208970,"link":"https://stackoverflow.com/questions/41208970/ubuntu-16-04-malloc-implementation-where-is-the-pointer-to-the-next-chunk","title":"Ubuntu 16.04 - malloc implementation. Where is the pointer to the next chunk?"},{"tags":["security","amazon-web-services","amazon-s3"],"owner":{"reputation":122,"user_id":2850437,"user_type":"registered","accept_rate":35,"profile_image":"https://www.gravatar.com/avatar/af51636fc213339dc751fa0e662d6971?s=128&d=identicon&r=PG&f=1","display_name":"Eric","link":"https://stackoverflow.com/users/2850437/eric"},"is_answered":true,"view_count":469,"answer_count":1,"score":0,"last_activity_date":1482070576,"creation_date":1482069040,"question_id":41208973,"link":"https://stackoverflow.com/questions/41208973/store-user-profile-pictures-securely-on-aws-s3","title":"Store User Profile Pictures Securely on AWS S3"},{"tags":["function","system-verilog","dynamic-arrays"],"owner":{"reputation":124,"user_id":6465067,"user_type":"registered","accept_rate":43,"profile_image":"https://www.gravatar.com/avatar/0088f0148ba962c088e9822b2601fa6c?s=128&d=identicon&r=PG&f=1","display_name":"sara8d","link":"https://stackoverflow.com/users/6465067/sara8d"},"is_answered":true,"view_count":102,"answer_count":1,"score":0,"last_activity_date":1482137519,"creation_date":1482069117,"question_id":41208981,"link":"https://stackoverflow.com/questions/41208981/systemveilog-pass-array-of-unknown-size","title":"systemVeilog - pass array of unknown size"},{"tags":["c++"],"owner":{"reputation":124,"user_id":5936816,"user_type":"registered","accept_rate":83,"profile_image":"https://graph.facebook.com/1163996213630202/picture?type=large","display_name":"Yoanna Murdzheva","link":"https://stackoverflow.com/users/5936816/yoanna-murdzheva"},"is_answered":true,"view_count":201,"accepted_answer_id":41209050,"answer_count":3,"score":-6,"last_activity_date":1482116524,"creation_date":1482069127,"question_id":41208984,"link":"https://stackoverflow.com/questions/41208984/printing-n-pairs-of-prime-numbers-c","title":"Printing n pairs of prime numbers, C++"},{"tags":["caffe","pycaffe","matcaffe"],"owner":{"reputation":559,"user_id":6494707,"user_type":"registered","accept_rate":41,"profile_image":"https://www.gravatar.com/avatar/a5a0386bef704f985d4eef036075b3fa?s=128&d=identicon&r=PG&f=1","display_name":"S.EB","link":"https://stackoverflow.com/users/6494707/s-eb"},"is_answered":true,"view_count":392,"accepted_answer_id":48008373,"answer_count":1,"score":2,"last_activity_date":1514467633,"creation_date":1482069157,"last_edit_date":1514467163,"question_id":41208990,"link":"https://stackoverflow.com/questions/41208990/how-did-you-run-fcn-code-semantic-segmentation","title":"How did you run FCN code semantic segmentation?"},{"tags":["java","android","copy","file-extension"],"owner":{"reputation":79,"user_id":6203436,"user_type":"registered","accept_rate":67,"profile_image":"https://www.gravatar.com/avatar/753da92bfaf5513318dd7c3cb42e36e2?s=128&d=identicon&r=PG&f=1","display_name":"omini data","link":"https://stackoverflow.com/users/6203436/omini-data"},"is_answered":false,"view_count":83,"answer_count":0,"score":0,"last_activity_date":1482113182,"creation_date":1482069225,"last_edit_date":1482113182,"question_id":41208998,"link":"https://stackoverflow.com/questions/41208998/java-copy-all-jpegs-from-a-folder-to-another-folder","title":"Java copy all JPEGs from a folder to another folder"},{"tags":["mips","mips32","qtspim"],"owner":{"reputation":96,"user_id":5249411,"user_type":"registered","accept_rate":86,"profile_image":"https://i.stack.imgur.com/pWaUR.png?s=128&g=1","display_name":"Aram Becker","link":"https://stackoverflow.com/users/5249411/aram-becker"},"is_answered":true,"view_count":291,"accepted_answer_id":41745702,"answer_count":2,"score":0,"last_activity_date":1484839880,"creation_date":1482069251,"last_edit_date":1482074787,"question_id":41209001,"link":"https://stackoverflow.com/questions/41209001/opening-file-always-returns-1-in-qtspim","title":"Opening file always returns &quot;-1&quot; in QtSpim"},{"tags":["c#","mysql","winforms"],"owner":{"reputation":3,"user_id":7312996,"user_type":"registered","profile_image":"https://lh3.googleusercontent.com/-dEzKzvdWlIA/AAAAAAAAAAI/AAAAAAAAAC0/Glgdp0XZieM/photo.jpg?sz=128","display_name":"Max Fedrych","link":"https://stackoverflow.com/users/7312996/max-fedrych"},"is_answered":true,"view_count":23,"accepted_answer_id":41209029,"answer_count":2,"score":0,"last_activity_date":1482083214,"creation_date":1482069258,"last_edit_date":1482083214,"question_id":41209003,"link":"https://stackoverflow.com/questions/41209003/how-to-check-that-id-which-i-put-from-textbox-does-not-exist-in-my-mysql-tabl","title":"How to check, that &quot;ID&quot; which i put from textbox does not exist in my MySql table?"},{"tags":["ios","swift","xcode"],"owner":{"reputation":8,"user_id":7313010,"user_type":"registered","profile_image":"https://graph.facebook.com/10154317558596359/picture?type=large","display_name":"Mirco Susan","link":"https://stackoverflow.com/users/7313010/mirco-susan"},"is_answered":true,"view_count":329,"accepted_answer_id":41209371,"answer_count":1,"score":1,"last_activity_date":1482073772,"creation_date":1482069293,"last_edit_date":1482070951,"question_id":41209005,"link":"https://stackoverflow.com/questions/41209005/type-uiimagepickercontrollersourcetype-has-no-member-photolibrary","title":"Type &#39;UIImagePickerControllerSourceType&#39; has no member &#39;photoLibrary&#39;"},{"tags":["css3","twitter-bootstrap-3","media-queries"],"owner":{"reputation":106,"user_id":5794350,"user_type":"registered","profile_image":"https://i.stack.imgur.com/kXL9X.jpg?s=128&g=1","display_name":"Balloonatic","link":"https://stackoverflow.com/users/5794350/balloonatic"},"is_answered":true,"view_count":246,"answer_count":1,"score":1,"last_activity_date":1511362009,"creation_date":1482069306,"question_id":41209008,"link":"https://stackoverflow.com/questions/41209008/media-queries-not-working-as-expected-hidden-classes-bootstrap","title":"Media queries not working as expected (Hidden classes Bootstrap)"},{"tags":["java","login","jsoup"],"owner":{"reputation":408,"user_id":1267491,"user_type":"registered","accept_rate":67,"profile_image":"https://www.gravatar.com/avatar/362ba7d45856130e5f8b090c7e59e577?s=128&d=identicon&r=PG","display_name":"Mohammad Saifullah","link":"https://stackoverflow.com/users/1267491/mohammad-saifullah"},"is_answered":true,"view_count":488,"answer_count":1,"score":0,"last_activity_date":1501829217,"creation_date":1482069318,"last_edit_date":1495540388,"question_id":41209009,"link":"https://stackoverflow.com/questions/41209009/jsoup-automatically-login-to-a-website","title":"JSOUP Automatically Login to a website"},{"tags":["assembly","x86","jmp"],"owner":{"reputation":6,"user_id":7312969,"user_type":"registered","profile_image":"https://www.gravatar.com/avatar/70378b5096e33a495a380900f03fb687?s=128&d=identicon&r=PG&f=1","display_name":"user7312969","link":"https://stackoverflow.com/users/7312969/user7312969"},"is_answered":true,"view_count":137,"answer_count":1,"score":1,"last_activity_date":1482283609,"creation_date":1482069322,"last_edit_date":1482089264,"question_id":41209013,"link":"https://stackoverflow.com/questions/41209013/reading-assembly-jump-and-compare-statements","title":"Reading assembly, jump and compare statements"},{"tags":["elixir","phoenix-framework"],"owner":{"reputation":2765,"user_id":1009465,"user_type":"registered","accept_rate":92,"profile_image":"https://www.gravatar.com/avatar/303789f7a429555b9408e075cec184ff?s=128&d=identicon&r=PG","display_name":"MartinElvar","link":"https://stackoverflow.com/users/1009465/martinelvar"},"is_answered":true,"view_count":246,"accepted_answer_id":41210643,"answer_count":1,"score":0,"last_activity_date":1482079836,"creation_date":1482069322,"question_id":41209012,"link":"https://stackoverflow.com/questions/41209012/semantic-ui-loading-fonts-404","title":"Semantic UI, loading fonts, 404"},{"tags":["javascript","jquery"],"owner":{"reputation":8,"user_id":7275166,"user_type":"registered","profile_image":"https://www.gravatar.com/avatar/cf07ea3cef8e94da6446e202bb2cead1?s=128&d=identicon&r=PG&f=1","display_name":"micmit","link":"https://stackoverflow.com/users/7275166/micmit"},"is_answered":true,"view_count":41,"accepted_answer_id":41209869,"answer_count":1,"score":1,"last_activity_date":1482074862,"creation_date":1482069369,"last_edit_date":1482070762,"question_id":41209017,"link":"https://stackoverflow.com/questions/41209017/how-do-i-toggle-li-sortable-status-when-it-is-an-image","title":"How do i toggle &lt;li&gt; sortable status when it is an image"},{"tags":["r","plot"],"owner":{"reputation":1813,"user_id":4865723,"user_type":"registered","accept_rate":80,"profile_image":"https://www.gravatar.com/avatar/2a94d3ff9e3ae1ddf8c09b8511ba76f0?s=128&d=identicon&r=PG&f=1","display_name":"buhtz","link":"https://stackoverflow.com/users/4865723/buhtz"},"is_answered":true,"view_count":83,"accepted_answer_id":41209405,"answer_count":1,"score":0,"last_activity_date":1482072579,"creation_date":1482069375,"last_edit_date":1482072579,"question_id":41209018,"link":"https://stackoverflow.com/questions/41209018/group-points-in-a-stacked-stripchart-1-d-scatter-plot-in-r","title":"Group points in a stacked stripchart (1-D scatter plot) in R"},{"tags":["c#","winforms","listview"],"owner":{"reputation":1,"user_id":7115125,"user_type":"registered","accept_rate":75,"profile_image":"https://www.gravatar.com/avatar/04cedbf093abad328c12d32a5ca4f7c0?s=128&d=identicon&r=PG","display_name":"Memories","link":"https://stackoverflow.com/users/7115125/memories"},"is_answered":true,"view_count":36,"accepted_answer_id":41209184,"answer_count":2,"score":0,"last_activity_date":1482072128,"creation_date":1482069391,"question_id":41209021,"link":"https://stackoverflow.com/questions/41209021/items-arent-showing-up-in-listview","title":"Items aren&#39;t showing up in ListView"},{"tags":["jquery","resize","location","height","width"],"owner":{"reputation":54,"user_id":4593389,"user_type":"registered","accept_rate":50,"profile_image":"https://lh4.googleusercontent.com/-61BlWOuVy4U/AAAAAAAAAAI/AAAAAAAAAD8/OZ-vf6nQWWw/photo.jpg?sz=128","display_name":"ALBADI","link":"https://stackoverflow.com/users/4593389/albadi"},"is_answered":true,"view_count":260,"accepted_answer_id":41209698,"answer_count":1,"score":1,"last_activity_date":1482073687,"creation_date":1482069394,"last_edit_date":1482072639,"question_id":41209022,"link":"https://stackoverflow.com/questions/41209022/jquery-location-reload-when-only-width-of-window-change","title":"jQuery location, reload when only width of window change"},{"tags":["javascript","python","selenium","scrapy","screen-scraping"],"owner":{"reputation":559,"user_id":2056878,"user_type":"registered","accept_rate":47,"profile_image":"https://i.stack.imgur.com/IZFw8.jpg?s=128&g=1","display_name":"occulti","link":"https://stackoverflow.com/users/2056878/occulti"},"is_answered":true,"view_count":83,"accepted_answer_id":41213275,"answer_count":1,"score":1,"last_activity_date":1482098010,"creation_date":1482069474,"last_edit_date":1482071407,"question_id":41209030,"link":"https://stackoverflow.com/questions/41209030/python-how-to-scrape-a-page-to-get-an-information-that-will-be-used-to-scrape","title":"Python : How to scrape a page to get an information that will be used to scrape another one, and so on?"},{"tags":["android","bottombar"],"owner":{"reputation":109,"user_id":6888434,"user_type":"registered","accept_rate":78,"profile_image":"https://i.stack.imgur.com/NpKTT.jpg?s=128&g=1","display_name":"EmilyR","link":"https://stackoverflow.com/users/6888434/emilyr"},"is_answered":false,"view_count":55,"answer_count":0,"score":1,"last_activity_date":1482069536,"creation_date":1482069536,"question_id":41209034,"link":"https://stackoverflow.com/questions/41209034/how-i-can-hide-the-bottom-bar-after-it-reappear","title":"How I can hide the bottom bar after it reappear"},{"tags":["javascript","jquery"],"owner":{"reputation":2158,"user_id":1019588,"user_type":"registered","accept_rate":81,"profile_image":"https://www.gravatar.com/avatar/8b62434074480584cb2fc046a418dff6?s=128&d=identicon&r=PG","display_name":"hellohellosharp","link":"https://stackoverflow.com/users/1019588/hellohellosharp"},"is_answered":false,"view_count":22,"answer_count":1,"score":0,"last_activity_date":1482069804,"creation_date":1482069543,"question_id":41209036,"link":"https://stackoverflow.com/questions/41209036/performance-issues-with-appendto-to-create-tables-dynamically","title":"Performance issues with appendTo() to create tables dynamically"},{"tags":["javascript","angularjs","angular","ios-simulator","angular-cli"],"owner":{"reputation":1,"user_id":7313021,"user_type":"registered","profile_image":"https://www.gravatar.com/avatar/90e74f67efdc3f58cfb3e7ae806fd9f4?s=128&d=identicon&r=PG&f=1","display_name":"ap087","link":"https://stackoverflow.com/users/7313021/ap087"},"is_answered":false,"view_count":84,"answer_count":1,"score":0,"last_activity_date":1482326292,"creation_date":1482069558,"last_edit_date":1482077964,"question_id":41209037,"link":"https://stackoverflow.com/questions/41209037/index-js-map-file-missing-when-starting-an-angular-cli-app-in-ipad-simulator","title":"Index.js.map file missing when starting an angular-cli app in iPad-simulator"}]