[{"tags":["angular","d3.js"],"owner":{"reputation":23,"user_id":6895207,"user_type":"registered","profile_image":"https://www.gravatar.com/avatar/41124ed59a53f47704709ea610742f35?s=128&d=identicon&r=PG&f=1","display_name":"d k","link":"https://stackoverflow.com/users/6895207/d-k"},"is_answered":true,"view_count":762,"accepted_answer_id":40903153,"answer_count":1,"score":3,"last_activity_date":1480569684,"creation_date":1480565928,"last_edit_date":1480568112,"question_id":40902581,"link":"https://stackoverflow.com/questions/40902581/how-to-deal-with-onchanges-that-requires-an-afterviewinit","title":"how to deal with OnChanges that requires an AfterViewInit"},{"tags":["c#","wpf","design-patterns","publish-subscribe","eventaggregator"],"owner":{"reputation":37,"user_id":6738226,"user_type":"registered","accept_rate":71,"profile_image":"https://www.gravatar.com/avatar/8c7bfdd599703d0f59b8adb35c33384d?s=128&d=identicon&r=PG&f=1","display_name":"Milleu","link":"https://stackoverflow.com/users/6738226/milleu"},"is_answered":false,"view_count":35,"answer_count":1,"score":0,"last_activity_date":1480574086,"creation_date":1480565940,"last_edit_date":1480566247,"question_id":40902582,"link":"https://stackoverflow.com/questions/40902582/dynamicly-assign-pub-subs-of-different-event-types-to-multiple-aggregator","title":"Dynamicly assign pub/subs of different event types to multiple aggregator"},{"tags":["ios","frameworks","swift2"],"owner":{"reputation":16,"user_id":5750522,"user_type":"registered","profile_image":"https://www.gravatar.com/avatar/3a12af7805426bed453d522b900c9e7e?s=128&d=identicon&r=PG&f=1","display_name":"iOS Akatsuki","link":"https://stackoverflow.com/users/5750522/ios-akatsuki"},"is_answered":false,"view_count":320,"answer_count":1,"score":1,"last_activity_date":1496226035,"creation_date":1480565948,"last_edit_date":1480798166,"question_id":40902585,"link":"https://stackoverflow.com/questions/40902585/how-to-call-objective-c-libraries-in-dynamic-framework-swift","title":"How to call Objective-C libraries in dynamic framework Swift?"},{"tags":["android","android-relativelayout"],"owner":{"reputation":11,"user_id":7234119,"user_type":"registered","profile_image":"https://www.gravatar.com/avatar/3abe0dcc0ab2c31ce276a9453b5feb74?s=128&d=identicon&r=PG&f=1","display_name":"newtoandroid","link":"https://stackoverflow.com/users/7234119/newtoandroid"},"is_answered":true,"view_count":322,"answer_count":1,"score":2,"last_activity_date":1480566924,"creation_date":1480565960,"question_id":40902586,"link":"https://stackoverflow.com/questions/40902586/adding-views-programatically-to-a-relative-layout-within-a-scrollview","title":"Adding views programatically to a relative layout within a scrollview"},{"tags":["javascript","jquery","html","css"],"owner":{"reputation":20,"user_id":6432935,"user_type":"registered","accept_rate":100,"profile_image":"https://www.gravatar.com/avatar/d8fbfa4f2735ea35c4d1302ac920529d?s=128&d=identicon&r=PG&f=1","display_name":"Learning to Code","link":"https://stackoverflow.com/users/6432935/learning-to-code"},"is_answered":true,"view_count":83,"accepted_answer_id":40902811,"answer_count":2,"score":2,"last_activity_date":1483408039,"creation_date":1480565970,"last_edit_date":1483408039,"question_id":40902588,"link":"https://stackoverflow.com/questions/40902588/how-to-scroll-up-a-div-when-hovering-over-another-element","title":"How to scroll up a div when hovering over another element"},{"tags":["javascript","html","css","google-chrome","webkit"],"owner":{"reputation":374,"user_id":1440841,"user_type":"registered","accept_rate":60,"profile_image":"https://www.gravatar.com/avatar/500fee28820d79a1813648ef53675f6d?s=128&d=identicon&r=PG","display_name":"John Auld","link":"https://stackoverflow.com/users/1440841/john-auld"},"is_answered":false,"view_count":72,"answer_count":1,"score":0,"last_activity_date":1480566651,"creation_date":1480565996,"question_id":40902596,"link":"https://stackoverflow.com/questions/40902596/how-can-i-speed-up-html-manipulation-via-javascript-and-or-improve-rendering-sp","title":"How can I speed up HTML manipulation via Javascript, and/or improve rendering speed of animations?"},{"tags":["python","python-2.7","stripe-payments","stripe-connect"],"owner":{"reputation":538,"user_id":658209,"user_type":"registered","accept_rate":75,"profile_image":"https://www.gravatar.com/avatar/f4e7d74b5fdc316bc114f493882562ce?s=128&d=identicon&r=PG","display_name":"Priyam","link":"https://stackoverflow.com/users/658209/priyam"},"is_answered":true,"view_count":140,"accepted_answer_id":40902738,"answer_count":1,"score":0,"last_activity_date":1480566982,"creation_date":1480566006,"question_id":40902598,"link":"https://stackoverflow.com/questions/40902598/stripe-refunds-error","title":"Stripe Refunds Error"},{"tags":["jasper-reports","jaspersoft-studio"],"owner":{"reputation":1412,"user_id":2782001,"user_type":"registered","accept_rate":58,"profile_image":"https://www.gravatar.com/avatar/99b4113e1135e04aaf19e52d8e0615d0?s=128&d=identicon&r=PG&f=1","display_name":"user2782001","link":"https://stackoverflow.com/users/2782001/user2782001"},"is_answered":true,"view_count":1602,"protected_date":1495109143,"accepted_answer_id":40922182,"answer_count":1,"score":2,"last_activity_date":1495660933,"creation_date":1480566038,"last_edit_date":1480634611,"question_id":40902602,"link":"https://stackoverflow.com/questions/40902602/jaspersoft-studio-how-to-use-collection-of-java-beans-in-data-adapter","title":"Jaspersoft Studio: How to use Collection of Java Beans in data adapter"},{"tags":["excel","vba","excel-vba","excel-2013"],"owner":{"reputation":91,"user_id":7086614,"user_type":"registered","accept_rate":91,"profile_image":"https://www.gravatar.com/avatar/4fad256a51f36f252838afd4a50a17d3?s=128&d=identicon&r=PG&f=1","display_name":"SmallFries BigGuys","link":"https://stackoverflow.com/users/7086614/smallfries-bigguys"},"is_answered":true,"view_count":101,"accepted_answer_id":40905045,"answer_count":2,"score":1,"last_activity_date":1482165920,"creation_date":1480566045,"question_id":40902604,"link":"https://stackoverflow.com/questions/40902604/add-total-row-to-each-worksheet-in-workbook","title":"Add Total Row To Each Worksheet in Workbook"},{"tags":["javascript","angularjs"],"owner":{"reputation":1,"user_id":7234304,"user_type":"registered","profile_image":"https://www.gravatar.com/avatar/92543ae1f6a11c1383c35bb656a78765?s=128&d=identicon&r=PG&f=1","display_name":"Sara","link":"https://stackoverflow.com/users/7234304/sara"},"is_answered":false,"view_count":53,"answer_count":0,"score":0,"last_activity_date":1480566051,"creation_date":1480566051,"question_id":40902605,"link":"https://stackoverflow.com/questions/40902605/how-to-watch-scope-variable-in-parent-window-scope-from-child-popup-or-window","title":"How to Watch $scope variable in parent window scope from child popup or window"},{"tags":["c#","crystal-reports"],"owner":{"reputation":199,"user_id":3035133,"user_type":"registered","accept_rate":72,"profile_image":"https://i.stack.imgur.com/HRjzc.jpg?s=128&g=1","display_name":"user3035133","link":"https://stackoverflow.com/users/3035133/user3035133"},"is_answered":true,"view_count":40,"accepted_answer_id":40903948,"answer_count":1,"score":-1,"last_activity_date":1480576558,"creation_date":1480566088,"last_edit_date":1480576558,"question_id":40902609,"link":"https://stackoverflow.com/questions/40902609/saving-logon-information-when-loading-crystal-report-in-c","title":"Saving logon information when loading Crystal Report in C#"},{"tags":["node.js","postgresql","http","angular","node-postgres"],"owner":{"reputation":4166,"user_id":2218253,"user_type":"registered","accept_rate":82,"profile_image":"https://i.stack.imgur.com/fyeY9.png?s=128&g=1","display_name":"wuno","link":"https://stackoverflow.com/users/2218253/wuno"},"is_answered":true,"view_count":49,"accepted_answer_id":40902998,"answer_count":1,"score":0,"last_activity_date":1480569389,"creation_date":1480566097,"last_edit_date":1480568776,"question_id":40902610,"link":"https://stackoverflow.com/questions/40902610/decrypting-data-from-database-before-sending-response-back-node-js","title":"Decrypting Data From Database Before Sending Response Back Node.js"},{"tags":["python","sqlite3"],"owner":{"reputation":18,"user_id":7187041,"user_type":"registered","profile_image":"https://www.gravatar.com/avatar/982051741b523eb0abf5cdceb9800d8f?s=128&d=identicon&r=PG&f=1","display_name":"Dominic","link":"https://stackoverflow.com/users/7187041/dominic"},"is_answered":true,"view_count":35,"accepted_answer_id":40902634,"answer_count":1,"score":1,"last_activity_date":1480566251,"creation_date":1480566118,"last_edit_date":1480566203,"question_id":40902616,"link":"https://stackoverflow.com/questions/40902616/python-sqlite3-want-to-iteratively-fetching-rows-but-code-is-pulling-every-oth","title":"Python SQLite3: want to iteratively fetching rows, but code is pulling every other row"},{"tags":["javascript","adobe","livecycle","livecycle-designer"],"owner":{"reputation":8,"user_id":7232175,"user_type":"registered","profile_image":"https://www.gravatar.com/avatar/44199d4a9b4c55889c6b9d11887811f4?s=128&d=identicon&r=PG&f=1","display_name":"jpee","link":"https://stackoverflow.com/users/7232175/jpee"},"is_answered":false,"view_count":58,"answer_count":2,"score":0,"last_activity_date":1481200131,"creation_date":1480566120,"last_edit_date":1480569436,"question_id":40902617,"link":"https://stackoverflow.com/questions/40902617/adobe-livecycle-set-access-state-for-column-in-dynamic-table","title":"Adobe Livecycle set access state for column in dynamic table"},{"tags":["c#"],"owner":{"reputation":13,"user_id":7234283,"user_type":"registered","profile_image":"https://lh3.googleusercontent.com/-oodobi-ndOQ/AAAAAAAAAAI/AAAAAAAAAA8/sLscw-f5eug/photo.jpg?sz=128","display_name":"Zech","link":"https://stackoverflow.com/users/7234283/zech"},"is_answered":true,"view_count":40,"accepted_answer_id":40902638,"answer_count":3,"score":1,"last_activity_date":1480566436,"creation_date":1480566126,"last_edit_date":1480566436,"question_id":40902618,"link":"https://stackoverflow.com/questions/40902618/could-someone-explain-why-converting-to-int-and-using-read-line-instead-of-read","title":"Could someone explain why Converting to int and using read line instead of Read fixed my issue?"},{"tags":["scala","slick","slick-3.0"],"owner":{"reputation":227,"user_id":1362485,"user_type":"registered","accept_rate":91,"profile_image":"https://www.gravatar.com/avatar/85b32b3a16a6ab2c1dec2bc3d086bff1?s=128&d=identicon&r=PG&f=1","display_name":"ps0604","link":"https://stackoverflow.com/users/1362485/ps0604"},"is_answered":true,"view_count":147,"accepted_answer_id":40927333,"answer_count":2,"score":0,"last_activity_date":1480675121,"creation_date":1480566132,"last_edit_date":1480675121,"question_id":40902621,"link":"https://stackoverflow.com/questions/40902621/run-transactionally-and-retrieve-result-in-future","title":"Run transactionally and retrieve result in Future"},{"tags":["android","textview","autolink"],"owner":{"reputation":77,"user_id":6868737,"user_type":"registered","accept_rate":75,"profile_image":"https://www.gravatar.com/avatar/a008fdb40ae544df3c9ca4ca530c5769?s=128&d=identicon&r=PG&f=1","display_name":"user6868737","link":"https://stackoverflow.com/users/6868737/user6868737"},"is_answered":true,"view_count":786,"answer_count":1,"score":1,"last_activity_date":1480578476,"creation_date":1480566136,"last_edit_date":1480576983,"question_id":40902622,"link":"https://stackoverflow.com/questions/40902622/how-to-remove-the-highlight-color-from-hyperlink-android","title":"How to remove the highlight color from hyperlink [Android]"},{"tags":["mysql","sql","database","mariadb"],"owner":{"reputation":895,"user_id":4251114,"user_type":"registered","accept_rate":70,"profile_image":"https://i.stack.imgur.com/3KNPN.jpg?s=128&g=1","display_name":"Sinux","link":"https://stackoverflow.com/users/4251114/sinux"},"is_answered":true,"view_count":811,"answer_count":1,"score":3,"last_activity_date":1487931775,"creation_date":1480566154,"question_id":40902624,"link":"https://stackoverflow.com/questions/40902624/why-doesnt-mysql-support-limit-in-all-any-some-subquery","title":"why doesn&#39;t MySQL support &#39;LIMIT &amp; IN/ALL/ANY/SOME subquery&#39;"},{"tags":["c#",".net"],"owner":{"reputation":108,"user_id":2531796,"user_type":"registered","accept_rate":83,"profile_image":"https://www.gravatar.com/avatar/29a5e87f77466fc670155620c57579be?s=128&d=identicon&r=PG","display_name":"Radoslav.Ivanov","link":"https://stackoverflow.com/users/2531796/radoslav-ivanov"},"is_answered":true,"view_count":486,"accepted_answer_id":40902663,"answer_count":2,"score":7,"last_activity_date":1480570157,"creation_date":1480566214,"last_edit_date":1480570157,"question_id":40902628,"link":"https://stackoverflow.com/questions/40902628/for-loop-variable-declaration-for-the-condition-in-net-source-code","title":"For loop variable declaration for the condition in .NET Source code"},{"tags":["java","android","android-studio","ubuntu","gradle"],"owner":{"reputation":50,"user_id":5019015,"user_type":"registered","accept_rate":50,"profile_image":"https://lh3.googleusercontent.com/-bzQKuf2PwDA/AAAAAAAAAAI/AAAAAAAAABM/EMGKswX8GSo/photo.jpg?sz=128","display_name":"karthik","link":"https://stackoverflow.com/users/5019015/karthik"},"is_answered":true,"view_count":224,"accepted_answer_id":40954856,"answer_count":2,"score":0,"last_activity_date":1483100031,"creation_date":1480566264,"last_edit_date":1480570970,"question_id":40902636,"link":"https://stackoverflow.com/questions/40902636/project-refresh-failed-android-studio-ubuntu","title":"Project Refresh failed - android studio - ubuntu"},{"tags":["verilog","inout"],"owner":{"reputation":36,"user_id":2330782,"user_type":"registered","accept_rate":0,"profile_image":"https://www.gravatar.com/avatar/cc44eef45375698c0fb88a4e4676fb5a?s=128&d=identicon&r=PG","display_name":"FatherOfNations","link":"https://stackoverflow.com/users/2330782/fatherofnations"},"is_answered":true,"view_count":5749,"answer_count":2,"score":0,"last_activity_date":1480843532,"creation_date":1480566277,"question_id":40902637,"link":"https://stackoverflow.com/questions/40902637/how-to-write-to-inout-port-and-read-from-inout-port-of-the-same-module","title":"How to write to inout port and read from inout port of the same module?"},{"tags":["regression","svm"],"owner":{"reputation":23,"user_id":5818237,"user_type":"registered","profile_image":"https://graph.facebook.com/1681648968773107/picture?type=large","display_name":"Golden Jiang","link":"https://stackoverflow.com/users/5818237/golden-jiang"},"is_answered":true,"view_count":385,"accepted_answer_id":40954182,"answer_count":1,"score":1,"last_activity_date":1480812311,"creation_date":1480566313,"question_id":40902641,"link":"https://stackoverflow.com/questions/40902641/error-when-tuning-a-support-vector-regression-model-in-r","title":"Error when tuning a support vector regression model in R"},{"tags":["html"],"owner":{"reputation":24,"user_id":6627161,"user_type":"registered","accept_rate":67,"profile_image":"https://i.stack.imgur.com/XfwvD.png?s=128&g=1","display_name":"NumaNuma","link":"https://stackoverflow.com/users/6627161/numanuma"},"is_answered":true,"view_count":23,"accepted_answer_id":40902732,"answer_count":2,"score":-2,"last_activity_date":1480566912,"creation_date":1480566346,"question_id":40902645,"link":"https://stackoverflow.com/questions/40902645/centered-html-content-box-with-a-width-and-height-limit","title":"CENTERED HTML content box with a width and height limit?"},{"tags":["javascript","angularjs"],"owner":{"reputation":174,"user_id":5722000,"user_type":"registered","accept_rate":81,"profile_image":"https://i.stack.imgur.com/OIL85.jpg?s=128&g=1","display_name":"imbagila","link":"https://stackoverflow.com/users/5722000/imbagila"},"is_answered":true,"view_count":275,"answer_count":1,"score":1,"last_activity_date":1480567267,"creation_date":1480566363,"last_edit_date":1480567267,"question_id":40902649,"link":"https://stackoverflow.com/questions/40902649/how-to-change-ng-model-dynamically-with-ng-click-controller-function","title":"How to change ng-model dynamically with ng-click controller function"},{"tags":["python-3.x"],"owner":{"reputation":1,"user_id":6923336,"user_type":"registered","profile_image":"https://i.stack.imgur.com/MYflN.jpg?s=128&g=1","display_name":"shark","link":"https://stackoverflow.com/users/6923336/shark"},"is_answered":false,"view_count":34,"answer_count":1,"score":0,"last_activity_date":1501408731,"creation_date":1480566404,"last_edit_date":1480918483,"question_id":40902654,"link":"https://stackoverflow.com/questions/40902654/python3-image-recognition-error","title":"Python3 image recognition error"},{"tags":["plot","gnuplot"],"owner":{"reputation":1,"user_id":7234245,"user_type":"registered","profile_image":"https://graph.facebook.com/1317624058299744/picture?type=large","display_name":"Gerson Barbosa","link":"https://stackoverflow.com/users/7234245/gerson-barbosa"},"is_answered":false,"view_count":70,"answer_count":1,"score":0,"last_activity_date":1489299728,"creation_date":1480566414,"last_edit_date":1489299728,"question_id":40902655,"link":"https://stackoverflow.com/questions/40902655/plots-different-sizes-of-radius-in-gnuplot","title":"Plots different sizes of radius in gnuplot"},{"tags":["zapier"],"owner":{"reputation":2492,"user_id":3147508,"user_type":"registered","accept_rate":89,"profile_image":"https://i.stack.imgur.com/DDd8J.jpg?s=128&g=1","display_name":"Ikbel","link":"https://stackoverflow.com/users/3147508/ikbel"},"is_answered":true,"view_count":257,"accepted_answer_id":40902694,"answer_count":2,"score":0,"last_activity_date":1486507189,"creation_date":1480566479,"question_id":40902660,"link":"https://stackoverflow.com/questions/40902660/zapier-scripting-error-cannot-find-module-moment","title":"Zapier Scripting - Error: Cannot find module &#39;moment&#39;"},{"tags":["python","regex","python-2.7","unicode","python-unicode"],"owner":{"reputation":13,"user_id":6514101,"user_type":"registered","profile_image":"https://graph.facebook.com/1024408977628841/picture?type=large","display_name":"Sandeep Chitta","link":"https://stackoverflow.com/users/6514101/sandeep-chitta"},"is_answered":true,"view_count":148,"answer_count":1,"score":2,"last_activity_date":1481681816,"creation_date":1480566492,"last_edit_date":1481579762,"question_id":40902662,"link":"https://stackoverflow.com/questions/40902662/find-all-the-matches-for-unicodes-in-a-string-in-python","title":"find all the matches for unicodes in a string in python"},{"tags":["regression","normalization","linear"],"owner":{"reputation":198,"user_id":363177,"user_type":"registered","profile_image":"https://www.gravatar.com/avatar/30e2d7f081f0b037d33beeeb53a5fe72?s=128&d=identicon&r=PG","display_name":"Andy Matteson","link":"https://stackoverflow.com/users/363177/andy-matteson"},"is_answered":false,"view_count":223,"answer_count":0,"score":1,"last_activity_date":1480566549,"creation_date":1480566549,"question_id":40902671,"link":"https://stackoverflow.com/questions/40902671/linear-regression-with-neural-networks-in-tensorflow-and-normalization","title":"Linear Regression with Neural Networks in Tensorflow and normalization"},{"tags":["c","string.h"],"owner":{"reputation":49,"user_id":6898752,"user_type":"registered","accept_rate":90,"profile_image":"https://graph.facebook.com/1087717028009249/picture?type=large","display_name":"STEPHEN bui","link":"https://stackoverflow.com/users/6898752/stephen-bui"},"is_answered":true,"view_count":58,"accepted_answer_id":40902837,"answer_count":3,"score":0,"last_activity_date":1480570480,"creation_date":1480566551,"last_edit_date":1480567334,"question_id":40902672,"link":"https://stackoverflow.com/questions/40902672/code-cant-get-an-n-digit-numbers-from-a-string-in-c","title":"Code can&#39;t get an n-digit numbers from a string in C"}]