[{"tags":["freebsd","disk","ssd"],"owner":{"reputation":11,"user_id":7256476,"user_type":"registered","profile_image":"https://i.stack.imgur.com/5iIPg.png?s=128&g=1","display_name":"xinyue","link":"https://stackoverflow.com/users/7256476/xinyue"},"is_answered":false,"view_count":553,"answer_count":1,"score":1,"last_activity_date":1486807668,"creation_date":1482090368,"last_edit_date":1483905904,"question_id":41212190,"link":"https://stackoverflow.com/questions/41212190/i-use-freebsd11-but-iops-is-very-very-poor-fio-tools","title":"I use freebsd11 but iops is very very poor (&#39;fio&#39; tools)"},{"tags":["apache","networking"],"owner":{"reputation":23,"user_id":5276825,"user_type":"registered","profile_image":"https://www.gravatar.com/avatar/76839266937ff1315a5150f1f8ed7d14?s=128&d=identicon&r=PG&f=1","display_name":"Mophead64","link":"https://stackoverflow.com/users/5276825/mophead64"},"is_answered":false,"view_count":13,"answer_count":0,"score":1,"last_activity_date":1482090415,"creation_date":1482090415,"question_id":41212197,"link":"https://stackoverflow.com/questions/41212197/use-apache-virtual-hosts-to-access-local-servers","title":"Use Apache virtual hosts to access local servers?"},{"tags":["c#","list"],"owner":{"reputation":24,"user_id":7291797,"user_type":"registered","accept_rate":67,"profile_image":"https://lh6.googleusercontent.com/-Hw6xbFFXAyE/AAAAAAAAAAI/AAAAAAAAABA/L_89n5Y5-8Q/photo.jpg?sz=128","display_name":"&#199;ağıl Uyar","link":"https://stackoverflow.com/users/7291797/%c3%87a%c4%9f%c4%b1l-uyar"},"is_answered":true,"view_count":30,"answer_count":1,"score":-3,"last_activity_date":1482091130,"creation_date":1482090430,"question_id":41212200,"link":"https://stackoverflow.com/questions/41212200/how-to-get-list-from-another-form-for-download-with-webclient","title":"How to get list from another form for download with webclient?"},{"tags":["c++","input","buffer","iostream","cin"],"owner":{"reputation":22,"user_id":6616363,"user_type":"registered","profile_image":"https://www.gravatar.com/avatar/9293d36afe3622178c6e6c06ef27b617?s=128&d=identicon&r=PG&f=1","display_name":"user6616363","link":"https://stackoverflow.com/users/6616363/user6616363"},"is_answered":true,"view_count":387,"accepted_answer_id":41212388,"answer_count":3,"score":2,"last_activity_date":1482092920,"creation_date":1482090465,"last_edit_date":1482091024,"question_id":41212202,"link":"https://stackoverflow.com/questions/41212202/cin-not-waiting-for-input-despite-cin-ignore","title":"Cin not waiting for input despite cin.ignore()"},{"tags":["android","android-layout","android-fragments","android-cardview"],"owner":{"reputation":19,"user_id":7279570,"user_type":"registered","accept_rate":12,"profile_image":"https://www.gravatar.com/avatar/cf55b120163ee4ba1b0d0f45f371536e?s=128&d=identicon&r=PG&f=1","display_name":"IamHuM","link":"https://stackoverflow.com/users/7279570/iamhum"},"is_answered":false,"view_count":122,"answer_count":1,"score":0,"last_activity_date":1482097713,"creation_date":1482090489,"question_id":41212209,"link":"https://stackoverflow.com/questions/41212209/fill-cardview-inside-screen-area","title":"Fill CardView inside screen area"},{"tags":["python"],"owner":{"reputation":217,"user_id":6936582,"user_type":"registered","accept_rate":100,"profile_image":"https://i.stack.imgur.com/f4zLW.png?s=128&g=1","display_name":"BERA","link":"https://stackoverflow.com/users/6936582/bera"},"is_answered":true,"view_count":60,"accepted_answer_id":41212296,"answer_count":5,"score":0,"last_activity_date":1482157150,"creation_date":1482090518,"last_edit_date":1482092624,"question_id":41212215,"link":"https://stackoverflow.com/questions/41212215/from-a-list-of-tuples-id-date-id-date-create-a-new-list-of-tuples-with","title":"From a list of tuples [(ID, date),(ID, date)..] create a new list of tuples with unique ID and most recent date"},{"tags":[".net","azure","asynchronous","timeout","application-shutdown"],"owner":{"reputation":6180,"user_id":90859,"user_type":"registered","accept_rate":74,"profile_image":"https://www.gravatar.com/avatar/2123a66ff1a7b382e9007d36a5823153?s=128&d=identicon&r=PG","display_name":"UserControl","link":"https://stackoverflow.com/users/90859/usercontrol"},"is_answered":true,"view_count":253,"accepted_answer_id":41254762,"answer_count":1,"score":0,"last_activity_date":1482291901,"creation_date":1482090528,"question_id":41212216,"link":"https://stackoverflow.com/questions/41212216/graceful-shutdown-of-azure-worker-role","title":"Graceful shutdown of Azure worker role"},{"tags":["ios","swift","xcode","uicollectionview","uicollectionviewcell"],"owner":{"reputation":48,"user_id":6227328,"user_type":"registered","accept_rate":43,"profile_image":"https://www.gravatar.com/avatar/f06f8d1bec4a75e1f20039af06d7f3c0?s=128&d=identicon&r=PG&f=1","display_name":"gianni","link":"https://stackoverflow.com/users/6227328/gianni"},"is_answered":true,"view_count":273,"accepted_answer_id":41212581,"answer_count":1,"score":2,"last_activity_date":1482093117,"creation_date":1482090529,"question_id":41212217,"link":"https://stackoverflow.com/questions/41212217/uicollectionview-cell-issue-swift","title":"UIcollectionview cell issue Swift"},{"tags":["jquery","ajax","asp.net-mvc"],"owner":{"reputation":153,"user_id":4593160,"user_type":"registered","accept_rate":48,"profile_image":"https://www.gravatar.com/avatar/dcba14c4754f81208f9cad9723b88e71?s=128&d=identicon&r=PG&f=1","display_name":"Pow4Pow5","link":"https://stackoverflow.com/users/4593160/pow4pow5"},"is_answered":true,"view_count":62,"answer_count":1,"score":2,"last_activity_date":1482134003,"creation_date":1482090538,"last_edit_date":1482134003,"question_id":41212218,"link":"https://stackoverflow.com/questions/41212218/asp-net-mvc-ajax-function-keep-failing","title":"ASP.NET MVC Ajax function keep failing?"},{"tags":["java","heroku","deployment"],"owner":{"reputation":8,"user_id":5908928,"user_type":"registered","profile_image":"https://lh3.googleusercontent.com/-D51B2fGuU4Q/AAAAAAAAAAI/AAAAAAAAABc/oKYn0Pn_ozg/photo.jpg?sz=128","display_name":"Naughty Fox","link":"https://stackoverflow.com/users/5908928/naughty-fox"},"is_answered":true,"view_count":288,"answer_count":2,"score":0,"last_activity_date":1482858581,"creation_date":1482090564,"question_id":41212221,"link":"https://stackoverflow.com/questions/41212221/trouble-deploying-java-web-app-to-heroku","title":"Trouble deploying java web app to Heroku"},{"tags":["php","mysql"],"owner":{"reputation":11,"user_id":5426406,"user_type":"registered","profile_image":"https://www.gravatar.com/avatar/8e4e92ac362dd656251931b57a6ee0ca?s=128&d=identicon&r=PG&f=1","display_name":"WilliamDelphi","link":"https://stackoverflow.com/users/5426406/williamdelphi"},"is_answered":true,"view_count":66,"accepted_answer_id":41212364,"answer_count":1,"score":0,"last_activity_date":1482153879,"creation_date":1482090570,"last_edit_date":1482151668,"question_id":41212224,"link":"https://stackoverflow.com/questions/41212224/why-wont-my-data-go-into-my-database","title":"Why won&#39;t my data go into my database?"},{"tags":["html","css"],"owner":{"reputation":1,"user_id":7313880,"user_type":"registered","profile_image":"https://www.gravatar.com/avatar/781ba817e01a66ae5b6300f20bd53bf4?s=128&d=identicon&r=PG&f=1","display_name":"Stephan H&#246;hn","link":"https://stackoverflow.com/users/7313880/stephan-h%c3%b6hn"},"is_answered":false,"view_count":25,"answer_count":1,"score":0,"last_activity_date":1482091466,"creation_date":1482090582,"question_id":41212228,"link":"https://stackoverflow.com/questions/41212228/how-to-center-inputs-and-button-in-webkit-browsers-without-shift","title":"How to center inputs and button in webkit browsers without shift?"},{"tags":["javascript","html","angularjs"],"owner":{"reputation":82,"user_id":7173451,"user_type":"registered","accept_rate":91,"profile_image":"https://www.gravatar.com/avatar/fe45d200c4ef5cd8b68dc3c91936248f?s=128&d=identicon&r=PG&f=1","display_name":"Jue Debutat","link":"https://stackoverflow.com/users/7173451/jue-debutat"},"is_answered":false,"view_count":48,"answer_count":1,"score":0,"last_activity_date":1482183321,"creation_date":1482090585,"question_id":41212230,"link":"https://stackoverflow.com/questions/41212230/angularjs-template-doesnt-pull-data-from-controller","title":"AngularJS template doesn&#39;t pull data from controller"},{"tags":["javascript"],"owner":{"reputation":1430,"user_id":6242376,"user_type":"registered","accept_rate":43,"profile_image":"https://graph.facebook.com/582463495261362/picture?type=large","display_name":"Matt Corby","link":"https://stackoverflow.com/users/6242376/matt-corby"},"is_answered":false,"view_count":802,"answer_count":0,"score":1,"last_activity_date":1482090590,"creation_date":1482090590,"question_id":41212231,"link":"https://stackoverflow.com/questions/41212231/uncaught-typeerror-cannot-set-property-onclick-of-null-at-window-onload","title":"Uncaught TypeError: Cannot set property &#39;onclick&#39; of null at window.onload"},{"tags":["c#","sql","sql-server","visual-studio","tsql"],"owner":{"reputation":6275,"user_id":117700,"user_type":"registered","accept_rate":91,"profile_image":"https://www.gravatar.com/avatar/1a350b4a18da2ffab7bde4bc753909bd?s=128&d=identicon&r=PG","display_name":"l--&#39;&#39;&#39;&#39;&#39;&#39;---------&#39;&#39;&#39;&#39;&#39;&#39;&#39;&#39;&#39;&#39;&#39;&#39;","link":"https://stackoverflow.com/users/117700/l"},"is_answered":true,"view_count":47,"answer_count":2,"score":1,"last_activity_date":1482687287,"creation_date":1482090619,"last_edit_date":1495539961,"question_id":41212233,"link":"https://stackoverflow.com/questions/41212233/re-creating-blocked-environment-with-many-threads-and-high-concurrency","title":"re-creating blocked environment with many threads and high concurrency"},{"tags":["gmail","media-queries","html-email"],"owner":{"reputation":187,"user_id":4723005,"user_type":"registered","accept_rate":59,"profile_image":"https://www.gravatar.com/avatar/120adaf7a7f450eaa10c2f1332b46e66?s=128&d=identicon&r=PG&f=1","display_name":"Kwhitejr","link":"https://stackoverflow.com/users/4723005/kwhitejr"},"is_answered":false,"view_count":477,"answer_count":2,"score":1,"last_activity_date":1482193333,"creation_date":1482090651,"question_id":41212236,"link":"https://stackoverflow.com/questions/41212236/why-is-gmail-client-via-chrome-and-android-app-still-strip-style-tag-from-ht","title":"Why is gmail client (via Chrome and Android app) still strip &lt;style&gt; tag from HTML email?"},{"tags":["javascript","proxy","prototype","accessor","screeps"],"owner":{"reputation":115,"user_id":7308434,"user_type":"registered","accept_rate":75,"profile_image":"https://lh3.googleusercontent.com/-kUPzZ0KlJcg/AAAAAAAAAAI/AAAAAAAAALI/5bidmluGb7U/photo.jpg?sz=128","display_name":"Estecka","link":"https://stackoverflow.com/users/7308434/estecka"},"is_answered":true,"view_count":118,"accepted_answer_id":41649488,"answer_count":1,"score":1,"last_activity_date":1485111812,"creation_date":1482090703,"last_edit_date":1485111812,"question_id":41212242,"link":"https://stackoverflow.com/questions/41212242/prototyping-the-accessors-of-all-possible-sub-properties","title":"Prototyping the accessors of ALL POSSIBLE sub-properties"},{"tags":["openstreetmap","overpass-api"],"owner":{"reputation":73,"user_id":4664842,"user_type":"registered","accept_rate":20,"profile_image":"https://www.gravatar.com/avatar/b1bf8309942254fde4a4202be5a07cd7?s=128&d=identicon&r=PG&f=1","display_name":"Passionate","link":"https://stackoverflow.com/users/4664842/passionate"},"is_answered":true,"view_count":422,"answer_count":2,"score":1,"last_activity_date":1482146754,"creation_date":1482090708,"question_id":41212244,"link":"https://stackoverflow.com/questions/41212244/given-a-osm-node-id-how-do-i-find-the-previous-x-points-in-all-directions","title":"Given a OSM node id, how do I find the previous x points in all directions?"},{"tags":["c","linux","linux-namespaces"],"owner":{"reputation":529,"user_id":2626865,"user_type":"registered","accept_rate":62,"profile_image":"https://www.gravatar.com/avatar/87b0bb4bfa092d80332688146d14f703?s=128&d=identicon&r=PG","display_name":"user19087","link":"https://stackoverflow.com/users/2626865/user19087"},"is_answered":false,"view_count":36,"answer_count":0,"score":2,"last_activity_date":1482091205,"creation_date":1482090741,"last_edit_date":1482091205,"question_id":41212248,"link":"https://stackoverflow.com/questions/41212248/failing-example-with-lwns-namespaces-in-operation-part-4-more-on-pid-namespa","title":"Failing example with LWN&#39;s &quot;Namespaces in operation, part 4: more on PID namespaces&quot;"},{"tags":["javascript","node.js","for-loop","asynchronous","callback"],"owner":{"reputation":74,"user_id":4976280,"user_type":"registered","accept_rate":73,"profile_image":"https://www.gravatar.com/avatar/ed7c4f49a0685f41e9bbb11545c3338d?s=128&d=identicon&r=PG&f=1","display_name":"Ralph","link":"https://stackoverflow.com/users/4976280/ralph"},"is_answered":true,"view_count":4590,"accepted_answer_id":41212752,"answer_count":2,"score":4,"last_activity_date":1497127071,"creation_date":1482090741,"last_edit_date":1497127071,"question_id":41212249,"link":"https://stackoverflow.com/questions/41212249/node-wait-for-loop-to-finish","title":"Node - Wait for loop to finish?"},{"tags":["json","google-chrome-extension","manifest.json"],"owner":{"reputation":37,"user_id":7313891,"user_type":"registered","profile_image":"https://lh5.googleusercontent.com/-_ewR_IF08N8/AAAAAAAAAAI/AAAAAAAAAgw/e-IqqhxiaYo/photo.jpg?sz=128","display_name":"Laurent","link":"https://stackoverflow.com/users/7313891/laurent"},"is_answered":true,"view_count":690,"closed_date":1483524375,"accepted_answer_id":41212326,"answer_count":1,"score":1,"last_activity_date":1488396255,"creation_date":1482090758,"last_edit_date":1488396255,"question_id":41212250,"link":"https://stackoverflow.com/questions/41212250/manifest-is-not-valid-json-line-18-column-2-trailing-comma-not-allowed","closed_reason":"off-topic","title":"Manifest is not valid JSON. Line: 18, column: 2, Trailing comma not allowed"},{"tags":["ios","input","ios-simulator","chinese-locale"],"owner":{"reputation":73,"user_id":1009723,"user_type":"registered","accept_rate":38,"profile_image":"https://www.gravatar.com/avatar/3c838636434e38069dc72ba058d44314?s=128&d=identicon&r=PG","display_name":"Jonathan Rachlin","link":"https://stackoverflow.com/users/1009723/jonathan-rachlin"},"is_answered":true,"view_count":287,"accepted_answer_id":41212373,"answer_count":1,"score":1,"last_activity_date":1482093505,"creation_date":1482090760,"last_edit_date":1495535440,"question_id":41212252,"link":"https://stackoverflow.com/questions/41212252/chinese-input-in-ios-simulator","title":"Chinese input in iOS simulator"},{"tags":["ios","swift","uiviewcontroller","uiscrollview"],"owner":{"reputation":8,"user_id":5653883,"user_type":"registered","accept_rate":33,"profile_image":"https://www.gravatar.com/avatar/90d51f1e0847ecee6ffdac4bd8c87dcb?s=128&d=identicon&r=PG&f=1","display_name":"Martynas","link":"https://stackoverflow.com/users/5653883/martynas"},"is_answered":false,"view_count":311,"answer_count":1,"score":0,"last_activity_date":1482094663,"creation_date":1482090820,"last_edit_date":1482093576,"question_id":41212261,"link":"https://stackoverflow.com/questions/41212261/how-to-resize-scrollview-when-keyboard-appears","title":"How to resize ScrollView when keyboard appears?"},{"tags":["react-native"],"owner":{"reputation":3,"user_id":6785883,"user_type":"registered","profile_image":"https://www.gravatar.com/avatar/66f63696518e75ab7a59289faa4c5e6b?s=128&d=identicon&r=PG&f=1","display_name":"alfarandy","link":"https://stackoverflow.com/users/6785883/alfarandy"},"is_answered":false,"view_count":43,"answer_count":1,"score":0,"last_activity_date":1482096352,"creation_date":1482090867,"last_edit_date":1482091618,"question_id":41212265,"link":"https://stackoverflow.com/questions/41212265/react-native-function-issue","title":"React Native function issue"},{"tags":["node.js","events","asynchronous","control-flow"],"owner":{"reputation":1211,"user_id":1755511,"user_type":"registered","accept_rate":100,"profile_image":"https://www.gravatar.com/avatar/71fb684e198455750d9738b84770b81f?s=128&d=identicon&r=PG","display_name":"Ashbay","link":"https://stackoverflow.com/users/1755511/ashbay"},"is_answered":true,"view_count":1264,"accepted_answer_id":41312125,"answer_count":3,"score":4,"last_activity_date":1493138574,"creation_date":1482090876,"last_edit_date":1483110589,"question_id":41212267,"link":"https://stackoverflow.com/questions/41212267/wait-for-an-event-to-happen-before-sending-http-response-in-nodejs","title":"Wait for an event to happen before sending HTTP response in NodeJS?"},{"tags":["python","etl","google-cloud-dataflow"],"owner":{"reputation":27,"user_id":2565061,"user_type":"registered","accept_rate":80,"profile_image":"https://i.stack.imgur.com/GSSuC.png?s=128&g=1","display_name":"selectle","link":"https://stackoverflow.com/users/2565061/selectle"},"is_answered":true,"view_count":115,"accepted_answer_id":41229251,"answer_count":1,"score":0,"last_activity_date":1482174032,"creation_date":1482090909,"question_id":41212272,"link":"https://stackoverflow.com/questions/41212272/google-cloud-dataflow-consume-external-source","title":"Google Cloud Dataflow consume external source"},{"tags":["python","python-3.x","pandas"],"owner":{"reputation":38,"user_id":6437260,"user_type":"registered","accept_rate":86,"profile_image":"https://www.gravatar.com/avatar/c43edeef899721eaca382ac5ecb3d327?s=128&d=identicon&r=PG&f=1","display_name":"i2_","link":"https://stackoverflow.com/users/6437260/i2"},"is_answered":true,"view_count":3286,"accepted_answer_id":41213232,"answer_count":2,"score":0,"last_activity_date":1482097646,"creation_date":1482090910,"question_id":41212273,"link":"https://stackoverflow.com/questions/41212273/pandaspython-fill-empty-cells-with-with-previous-row-value","title":"Pandas(Python) : Fill empty cells with with previous row value?"},{"tags":["android","android-activity","service","lifecycle"],"owner":{"reputation":906,"user_id":1364750,"user_type":"registered","accept_rate":52,"profile_image":"https://www.gravatar.com/avatar/a27f23f28a98be5a8fd2cd8b3d61450b?s=128&d=identicon&r=PG","display_name":"Deukalion","link":"https://stackoverflow.com/users/1364750/deukalion"},"is_answered":false,"view_count":111,"answer_count":1,"score":0,"last_activity_date":1482470654,"creation_date":1482090910,"question_id":41212274,"link":"https://stackoverflow.com/questions/41212274/lifecycle-of-android-services-differs-between-phones","title":"Lifecycle of Android Services differs between phones"},{"tags":["c#","winforms","visual-studio","combobox","listbox"],"owner":{"reputation":1,"user_id":5153247,"user_type":"registered","profile_image":"https://i.stack.imgur.com/UsmlO.jpg?s=128&g=1","display_name":"taskle","link":"https://stackoverflow.com/users/5153247/taskle"},"is_answered":false,"view_count":217,"answer_count":0,"score":0,"last_activity_date":1482090957,"creation_date":1482090957,"question_id":41212279,"link":"https://stackoverflow.com/questions/41212279/c-adding-selected-combobox-item-to-listbox","title":"c# / Adding selected combobox item to listbox"},{"tags":["c#",".net","arrays"],"owner":{"reputation":95,"user_id":2724420,"user_type":"registered","accept_rate":100,"profile_image":"https://i.stack.imgur.com/ZbqPe.jpg?s=128&g=1","display_name":"pio","link":"https://stackoverflow.com/users/2724420/pio"},"is_answered":true,"view_count":106,"accepted_answer_id":41215361,"answer_count":2,"score":1,"last_activity_date":1482118039,"creation_date":1482090976,"last_edit_date":1482091329,"question_id":41212280,"link":"https://stackoverflow.com/questions/41212280/summing-int32-represented-by-byte-array-in-c","title":"summing Int32 represented by byte array in c#"}]